
[
  { "id": 1, "hitza": "abaraska", "sinonimoak": ["orrazea", "abaoa", "eztiorrazea"] },
  { "id": 2, "hitza": "abiapuntu", "sinonimoak": ["abiaburu", "hastapen", "hasiera"] },
  { "id": 3, "hitza": "abizenak", "sinonimoak": ["deiturak"] },
  { "id": 4, "hitza": "aburuz", "sinonimoak": ["ustez", "iritziz", "irudiko(z)"] },
  { "id": 5, "hitza": "adabakiak", "sinonimoak": ["txaplatak", "txatalak", "petatxuak"] },
  { "id": 6, "hitza": "adats", "sinonimoak": ["ilaje", "menats", "motots"] },
  { "id": 7, "hitza": "adeitsua", "sinonimoak": ["gizabidetsua", "xaloa", "atsegina"] },
  { "id": 8, "hitza": "adimen", "sinonimoak": ["ulermen", "adimendu", "endelgu"] },
  { "id": 9, "hitza": "adindua", "sinonimoak": ["edadetua", "atsotua", "adintsua"] },
  { "id": 10, "hitza": "adoretsu", "sinonimoak": ["gartsu", "kementsu", "bipil"] },
  { "id": 11, "hitza": "afaloste", "sinonimoak": ["afalondo"] },
  { "id": 12, "hitza": "afanez", "sinonimoak": ["joranez", "lehiaz", "gogoz"] },
  { "id": 13, "hitza": "aforoa", "sinonimoak": ["edukiera", "lekua", "tokia"] },
  { "id": 14, "hitza": "agergarririk", "sinonimoak": ["frogarik", "erakusgarririk", "adierazgartik"] },
  { "id": 15, "hitza": "agerkari", "sinonimoak": ["aldizkari"] },
  { "id": 16, "hitza": "agerkunde", "sinonimoak": ["agerpen", "agerraldi", "agertze"] },
  { "id": 17, "hitza": "agian", "sinonimoak": ["apika", "beharbada", "akaso"] },
  { "id": 18, "hitza": "agindu", "sinonimoak": ["prometatu", "hitzeman", "promes egin"] },
  { "id": 19, "hitza": "agintari", "sinonimoak": ["buruzagi", "buru", "nagusi"] },
  { "id": 20, "hitza": "agiraka", "sinonimoak": ["errieta", "haserre", "ahakar"] },
  { "id": 21, "hitza": "agiri", "sinonimoak": ["idazki", "dokumentu"] },
  { "id": 22, "hitza": "agitu", "sinonimoak": ["gertatu", "jazo", "iragan"] },
  { "id": 23, "hitza": "agorril", "sinonimoak": ["abuztu", "dagonil"] },
  { "id": 24, "hitza": "agorteak", "sinonimoak": ["lehorteak", "sikateak", "agorraldiak"] },
  { "id": 25, "hitza": "aguazilak", "sinonimoak": ["udaltzainak", "txinelak"] },
  { "id": 26, "hitza": "agudo", "sinonimoak": ["laster", "azkar", "fite"] },
  { "id": 27, "hitza": "agur", "sinonimoak": ["diosal", "adio"] },
  { "id": 28, "hitza": "agure", "sinonimoak": ["zahar", "adintsu", "aitona"] },
  { "id": 29, "hitza": "ahaideak", "sinonimoak": ["senideak", "senitartekoak", "familiakoak"] },
  { "id": 30, "hitza": "ahaire", "sinonimoak": ["doinu", "melodia"] },
  { "id": 31, "hitza": "ahal den lasterren", "sinonimoak": ["lehenbailehen", "albait arinen", "ahalik eta azkarren"] },
  { "id": 32, "hitza": "badaezpadako", "sinonimoak": ["zalantzazko", "duda-mudako", "ezbaiko"] },
  { "id": 33, "hitza": "bagak", "sinonimoak": ["uhinak", "olatuak"] },
  { "id": 34, "hitza": "bailarik", "sinonimoak": ["haranik", "ibarrik", "sakanik"] },
  { "id": 35, "hitza": "baina", "sinonimoak": ["ordea", "hala ere", "alabaina"] },
  { "id": 36, "hitza": "bakan", "sinonimoak": ["banaka", "urri", "eskas"] },
  { "id": 37, "hitza": "baldarkeria", "sinonimoak": ["dorpekeria", "trakeskeria"] },
  { "id": 38, "hitza": "baztertu", "sinonimoak": ["zokoratu", "alboratu", "bazterreratu"] },
  { "id": 39, "hitza": "begiluze", "sinonimoak": ["kuxkuxero", "nontzeberri", "ikusmiratzaile"] },
  { "id": 40, "hitza": "begirale", "sinonimoak": ["jagole", "zaintzaile", "artatzaile"] },
  { "id": 41, "hitza": "begiramen", "sinonimoak": ["begirune", "errespetu", "adeitasun"] },
  { "id": 42, "hitza": "belaunaldi", "sinonimoak": ["gizaldi"] },
  { "id": 43, "hitza": "beltzune", "sinonimoak": ["ubeldura", "ubelune", "belztasun"] },
  { "id": 44, "hitza": "beratu", "sinonimoak": ["bigundu", "leundu", "guritu"] },
  { "id": 45, "hitza": "bertute", "sinonimoak": ["dohain", "prestutasun"] },
  { "id": 46, "hitza": "betebeharra", "sinonimoak": ["zeregina", "eginkizuna", "eginbeharra"] },
  { "id": 47, "hitza": "beterik", "sinonimoak": ["lepo", "gainezka", "mukuru"] },
  { "id": 48, "hitza": "betilun", "sinonimoak": ["triste", "goibel", "hits"] },
  { "id": 49, "hitza": "bezatu", "sinonimoak": ["hezi", "mantsotu", "otzandu"] },
  { "id": 50, "hitza": "bider", "sinonimoak": ["aldiz"] },
  { "id": 51, "hitza": "bidezidor", "sinonimoak": ["bidexka", "xendra", "basabide"] },
  { "id": 52, "hitza": "bigun", "sinonimoak": ["leun", "guri", "samur"] },
  { "id": 53, "hitza": "bilakaera", "sinonimoak": ["eboluzio", "garapen", "eraldaketa"] },
  { "id": 54, "hitza": "bitxilorez", "sinonimoak": ["txibiritaz"] },
  { "id": 55, "hitza": "bizibide", "sinonimoak": ["ogibide", "lanbide", "ofizio"] },
  { "id": 56, "hitza": "biziki", "sinonimoak": ["arras", "oso", "biziro"] },
  { "id": 57, "hitza": "blai-blai", "sinonimoak": ["mela-mela", "busti-busti", "putzu-putzu"] },
  { "id": 58, "hitza": "bokarta", "sinonimoak": ["antxoa"] },
  { "id": 59, "hitza": "borda", "sinonimoak": ["etxola", "txabola"] },
  { "id": 60, "hitza": "bordion", "sinonimoak": ["urdanga", "puta", "emagaldu", "maritzar", "julis"] },
  { "id": 61, "hitza": "borondate", "sinonimoak": ["gogo", "nahi", "desira"] },
  { "id": 62, "hitza": "borragoma", "sinonimoak": ["ezabagoma", "goma"] },
  { "id": 63, "hitza": "bortizkeria", "sinonimoak": ["indarkeria", "gogorkeria", "bortxakeria"] },
  { "id": 64, "hitza": "bozkario", "sinonimoak": ["poz", "alegrantzia", "poztasun"] },
  { "id": 65, "hitza": "bultzatzaile", "sinonimoak": ["sustatzaile", "eragile"] },
  { "id": 66, "hitza": "burugabe", "sinonimoak": ["txoro", "burtzoro", "zentzugabe"] },
  { "id": 67, "hitza": "burugogorra", "sinonimoak": ["setatsua", "egoskorra", "tematia"] },
  { "id": 68, "hitza": "burutazio", "sinonimoak": ["ideia", "pentsamendu", "gomuta"] },
  { "id": 69, "hitza": "burutu", "sinonimoak": ["gauzatu", "obratu", "mamitu"] },
  { "id": 70, "hitza": "buruz buruko", "sinonimoak": ["eskuz eskuko", "banakako", "bakarkako"] },
  { "id": 71, "hitza": "buztana", "sinonimoak": ["isatsa"] },
  { "id": 72, "hitza": "dailuz", "sinonimoak": ["segaz", "kodainaz"] },
  { "id": 73, "hitza": "danbada", "sinonimoak": ["danbatekoa", "burrunba", "harrabotsa"] },
  { "id": 74, "hitza": "datu", "sinonimoak": ["argibide", "zehaztapen", "azalpen"] },
  { "id": 75, "hitza": "deblauki", "sinonimoak": ["bat-batean", "kolpetik", "supituki"] },
  { "id": 76, "hitza": "defendaezinak", "sinonimoak": ["eutsiezinak", "sostengaezinak"] },
  { "id": 77, "hitza": "deiadar", "sinonimoak": ["oihu", "aldarri", "garrasi"] },
  { "id": 78, "hitza": "deitoragarri", "sinonimoak": ["negargarri", "tamalgarri", "penagarri"] },
  { "id": 79, "hitza": "deklarazioetan", "sinonimoak": ["adierazpenetan", "jakinarazpenetan", "azalpenetan"] },
  { "id": 80, "hitza": "dema", "sinonimoak": ["apustu", "postura"] },
  { "id": 81, "hitza": "dena dela", "sinonimoak": ["nolanahi ere", "edonola ere", "dena den"] },
  { "id": 82, "hitza": "denda", "sinonimoak": ["saltoki", "postu", "saltegi"] },
  { "id": 83, "hitza": "deportatu", "sinonimoak": ["erbesteratu", "arroztu", "atzerriratu"] },
  { "id": 84, "hitza": "derrigorrezko", "sinonimoak": ["ezinbesteko", "nahitaezko", "halabeharrezko"] },
  { "id": 85, "hitza": "desberindu", "sinonimoak": ["bereizi", "bereiztu", "ezberdindu"] },
  { "id": 86, "hitza": "desenkusaren", "sinonimoak": ["aitzakiaren", "estakururen"] },
  { "id": 87, "hitza": "desira", "sinonimoak": ["nahia", "gogoa", "guraria"] },
  { "id": 88, "hitza": "deslai", "sinonimoak": ["egiteke", "solte"] },
  { "id": 89, "hitza": "destinoa", "sinonimoak": ["patua", "halabeharra", "zoria"] },
  { "id": 90, "hitza": "deusik", "sinonimoak": ["ezer(txo)", "tutik", "fitsik"] },
  { "id": 91, "hitza": "dezenterekin", "sinonimoak": ["nahikorekin", "askirekin", "askotxorekin"] },
  { "id": 92, "hitza": "dibortziatu", "sinonimoak": ["bereizi", "banandu", "bizi-alargundu"] },
  { "id": 93, "hitza": "dieta", "sinonimoak": ["jan-neurri", "jan-lege"] },
  { "id": 94, "hitza": "diferentzia", "sinonimoak": ["alde", "ezberdintasun", "desberdintasun"] },
  { "id": 95, "hitza": "dirukoi", "sinonimoak": ["diruzale", "zeken", "zikoitz"] },
  { "id": 96, "hitza": "dirutzekotan", "sinonimoak": ["aberastekotan", "dirutza egitekotan"] },
  { "id": 97, "hitza": "diruzalekeria", "sinonimoak": ["zekenkeria", "zikoizkeria"] },
  { "id": 98, "hitza": "distantzia", "sinonimoak": ["tarte", "bitarte"] },
  { "id": 99, "hitza": "dohakabeki", "sinonimoak": ["zoritzarrez", "tamalez", "maluruski", "ondikoz", "damurik"] },
  { "id": 100, "hitza": "doi-doi", "sinonimoak": ["ozta-ozta", "justu-justu"] },
  { "id": 101, "hitza": "doilortu", "sinonimoak": ["zitaldu", "zakartu", "petraldu"] },
  { "id": 102, "hitza": "donge", "sinonimoak": ["txar", "gaizto", "maltzur"] },
  { "id": 103, "hitza": "dorpe", "sinonimoak": ["trakets", "baldar", "baldres"] },
  { "id": 104, "hitza": "dotore", "sinonimoak": ["apain", "lirain", "txairo"] },
  { "id": 105, "hitza": "dragoiak", "sinonimoak": ["herensugeak"] },
  { "id": 106, "hitza": "drolekeriatan", "sinonimoak": ["txantxatan", "bromatan", "olgetatan"] },
  { "id": 107, "hitza": "dudarik", "sinonimoak": ["zalantzarik", "ezbairik"] },
  { "id": 108, "hitza": "dunbots", "sinonimoak": ["zarata", "zalaparta", "azantz"] },
  { "id": 109, "hitza": "dungulu", "sinonimoak": ["morokil", "ahi", "artahi"] },
  { "id": 110, "hitza": "durduzadura", "sinonimoak": ["nahasmendu", "nahaste", "laborri"] },
  { "id": 111, "hitza": "dutxulua", "sinonimoak": ["txorrota", "txotxa", "zipotza"] },
  { "id": 112, "hitza": "ebakera", "sinonimoak": ["ahoskera", "ahoskatze", "ahoskuntza"] },
  { "id": 113, "hitza": "ebakuntza", "sinonimoak": ["ebaketa", "operazio"] },
  { "id": 114, "hitza": "ebatsi", "sinonimoak": ["lapurtu", "ostu"] },
  { "id": 115, "hitza": "ebazpena", "sinonimoak": ["erabakia", "burubidea", "xedapena"] },
  { "id": 116, "hitza": "edagale", "sinonimoak": ["egarri", "egarbera", "egartsu"] },
  { "id": 117, "hitza": "edendu", "sinonimoak": ["pozoitu", "kutsatu"] },
  { "id": 118, "hitza": "ederki", "sinonimoak": ["ederto", "bapo", "primeran"] },
  { "id": 119, "hitza": "ederretsi", "sinonimoak": ["preziatu", "balioetsi", "estimatu"] },
  { "id": 120, "hitza": "edertu", "sinonimoak": ["liraindu", "zirastu", "ederreztatu"] },
  { "id": 121, "hitza": "edonor", "sinonimoak": ["nornahi", "edozein", "zeinahi"] },
  { "id": 122, "hitza": "edukazio", "sinonimoak": ["heziketa", "gizabide", "heziera"] },
  { "id": 123, "hitza": "egia-egiatan", "sinonimoak": ["bene-benetan", "alajaina", "alafede"] },
  { "id": 124, "hitza": "egiaztagiri", "sinonimoak": ["ziurtagiri", "frogagiri", "zuribide"] },
  { "id": 125, "hitza": "egikaritu", "sinonimoak": ["betearazi", "burutu", "obratu"] },
  { "id": 126, "hitza": "eginahal", "sinonimoak": ["ahalegin", "entsegua", "esfortzu"] },
  { "id": 127, "hitza": "eginkizun", "sinonimoak": ["betebehar", "zeregin", "lan"] },
  { "id": 128, "hitza": "egituratu", "sinonimoak": ["programatu", "eratu", "antolatu"] },
  { "id": 129, "hitza": "egoiliar", "sinonimoak": ["bizilagun", "etxetiar", "maizter"] },
  { "id": 130, "hitza": "egokiera", "sinonimoak": ["aukera", "parada", "abagune"] },
  { "id": 131, "hitza": "egonezin", "sinonimoak": ["urduritasun", "artegatasun", "kezka"] },
  { "id": 132, "hitza": "egonkorrik", "sinonimoak": ["iraunkorrik", "finkorik"] },
  { "id": 133, "hitza": "egoskorra", "sinonimoak": ["setatia", "burugogorra", "tematsua"] },
  { "id": 134, "hitza": "egotetxe", "sinonimoak": ["aterpetxe", "ostatu", "babesleku"] },
  { "id": 135, "hitza": "egotzi", "sinonimoak": ["leporatu", "bota", "gaineratu"] },
  { "id": 136, "hitza": "egunabar", "sinonimoak": ["egunsenti", "goizalde", "goiztiri"] },
  { "id": 137, "hitza": "egundoko", "sinonimoak": ["sekulako", "izugarrizko", "itzelezko"] },
  { "id": 138, "hitza": "ehortz", "sinonimoak": ["lurpera", "hobira"] },
  { "id": 139, "hitza": "eihera", "sinonimoak": ["errota", "bolu"] },
  { "id": 140, "hitza": "eite", "sinonimoak": ["itxura", "irudi", "jite"] },
  { "id": 141, "hitza": "ekain", "sinonimoak": ["bagil", "ereiaro"] },
  { "id": 142, "hitza": "ekoizlerik", "sinonimoak": ["sortzailerik", "produzitzailerik", "produktorerik"] },
  { "id": 143, "hitza": "ekortu", "sinonimoak": ["erraztatu", "eskobatu", "erratzez garbitu"] },
  { "id": 144, "hitza": "ekuru", "sinonimoak": ["lasai", "trankil", "patxadatsu"] },
  { "id": 145, "hitza": "elai", "sinonimoak": ["enara"] },
  { "id": 146, "hitza": "enbarazu", "sinonimoak": ["traba", "oztopo", "eragozpen"] },
  { "id": 147, "hitza": "enparauak", "sinonimoak": ["gainerakoak", "gainontzekoak", "uzkinak"] },
  { "id": 148, "hitza": "entzuten", "sinonimoak": ["aditzen"] },
  { "id": 149, "hitza": "entzutetsua", "sinonimoak": ["ospetsua", "famatua", "sonatua"] },
  { "id": 150, "hitza": "erabaki", "sinonimoak": ["zirt edo zart", "ebatzi", "xedatu"] },
  { "id": 151, "hitza": "erabat", "sinonimoak": ["guztiz", "zeharo", "arras"] },
  { "id": 152, "hitza": "erabilgarri", "sinonimoak": ["maneiagarri", "erabilerraz", "maneiukor"] },
  { "id": 153, "hitza": "eragin", "sinonimoak": ["sorrarazi", "izanarazi", "edukiarazi"] },
  { "id": 154, "hitza": "eragotzi", "sinonimoak": ["galarazi", "debekatu", "oztopatu"] },
  { "id": 155, "hitza": "erakusleihoz", "sinonimoak": ["erakustokiz"] },
  { "id": 156, "hitza": "eranskina", "sinonimoak": ["gehigarria", "osagarria"] },
  { "id": 157, "hitza": "erbestean", "sinonimoak": ["deserrian", "atzerrian"] },
  { "id": 158, "hitza": "erbinuderik", "sinonimoak": ["ogigaztarik"] },
  { "id": 159, "hitza": "erdeinagarriak", "sinonimoak": ["mespretxagarriak", "gaitzesgarriak", "baztergarriak"] },
  { "id": 160, "hitza": "erdietsitako", "sinonimoak": ["lortutako", "eskuratutako", "jadetsitako"] },
  { "id": 161, "hitza": "ergela", "sinonimoak": ["leloa", "tentela", "kaikua"] },
  { "id": 162, "hitza": "erpin", "sinonimoak": ["tontor", "gailur", "gain"] },
  { "id": 163, "hitza": "errieta", "sinonimoak": ["haserre", "agiraka", "ahakar"] },
  { "id": 164, "hitza": "errukirik", "sinonimoak": ["gupidarik", "urrikalmendurik", "errukitasunik"] },
  { "id": 165, "hitza": "etxekotu", "sinonimoak": ["bertakotu", "lekukotu", "tokikotu"] },
  { "id": 166, "hitza": "eutsi", "sinonimoak": ["heldu", "oratu", "lotu"] },
  { "id": 167, "hitza": "ezetsi", "sinonimoak": ["ukatu", "baztertu", "errefusatu"] },
  { "id": 168, "hitza": "ezinbestez", "sinonimoak": ["halabeharrez", "nahitaez", "derrigorrean"] },
  { "id": 169, "hitza": "ezinikusi", "sinonimoak": ["gorroto", "herra", "higuin"] },
  { "id": 170, "hitza": "ezizena", "sinonimoak": ["goitizena", "izengoitia", "gaitzizena"] },
  { "id": 171, "hitza": "ezustea", "sinonimoak": ["ustekabea"] },
  { "id": 172, "hitza": "faborez", "sinonimoak": ["mesedez", "arren", "otoi"] },
  { "id": 173, "hitza": "faltak", "sinonimoak": ["gabeziak", "ezak", "eskasiak"] },
  { "id": 174, "hitza": "fama", "sinonimoak": ["ospe", "entzute", "omen"] },
  { "id": 175, "hitza": "familiarteko", "sinonimoak": ["senide", "senitarteko", "ahaide"] },
  { "id": 176, "hitza": "fededunagoak", "sinonimoak": ["sinestedunagoak", "sinestunagoak", "sinesleagoak"] },
  { "id": 177, "hitza": "fereka", "sinonimoak": ["laztan", "txera"] },
  { "id": 178, "hitza": "festak", "sinonimoak": ["jaiak", "bestak"] },
  { "id": 179, "hitza": "fidela", "sinonimoak": ["leiala", "zintzoa", "ona"] },
  { "id": 180, "hitza": "fildak", "sinonimoak": ["zarpailak", "piltzarrak", "zarpak"] },
  { "id": 181, "hitza": "finagoak", "sinonimoak": ["trebeagoak", "zintzoagoak", "hobeak"] },
  { "id": 182, "hitza": "finkatu", "sinonimoak": ["ezarri", "zehaztu", "mugatu"] },
  { "id": 183, "hitza": "finkoak", "sinonimoak": ["tinkoak", "irmoak", "zurrunak"] },
  { "id": 184, "hitza": "fitsik", "sinonimoak": ["tutik", "deusik", "zipitzik"] },
  { "id": 185, "hitza": "flakatu", "sinonimoak": ["argaldu", "mehetu", "lerdendu"] },
  { "id": 186, "hitza": "flako", "sinonimoak": ["ahul", "makal", "indarge"] },
  { "id": 187, "hitza": "formala", "sinonimoak": ["zintzoa", "zentzuduna", "prestua"] },
  { "id": 188, "hitza": "franko", "sinonimoak": ["asko", "ugari", "anitz"] },
  { "id": 189, "hitza": "fresko", "sinonimoak": ["hozkirri", "hozgiro", "freskura"] },
  { "id": 190, "hitza": "frogatzeko", "sinonimoak": ["egiaztatzeko", "ziurtatzeko", "adierazteko"] },
  { "id": 191, "hitza": "funts", "sinonimoak": ["oinarri", "zentzu", "zimendu"] },
  { "id": 192, "hitza": "gaberik", "sinonimoak": ["barik", "gabetarik"] },
  { "id": 193, "hitza": "Gabonak", "sinonimoak": ["Eguberriak"] },
  { "id": 194, "hitza": "gailendu", "sinonimoak": ["nagusitu", "nabarmendu", "gailen gelditu"] },
  { "id": 195, "hitza": "gain", "sinonimoak": ["gainera", "lekora", "landa"] },
  { "id": 196, "hitza": "gainazal", "sinonimoak": ["azalera", "gainaldea", "hedadura"] },
  { "id": 197, "hitza": "gaineratu", "sinonimoak": ["gehitu", "erantsi"] },
  { "id": 198, "hitza": "gaitasun", "sinonimoak": ["trebetasun", "iaiotasun", "abilezia"] },
  { "id": 199, "hitza": "gaitu", "sinonimoak": ["prestatu", "gertatu", "egokitu"] },
  { "id": 200, "hitza": "gaitza", "sinonimoak": ["zaila", "nekeza"] },
  { "id": 201, "hitza": "gaixoek", "sinonimoak": ["eriek", "pazienteek"] },
  { "id": 202, "hitza": "gaiztotu", "sinonimoak": ["zoldu", "zornatu", "gaizkoatu"] },
  { "id": 203, "hitza": "galbidea", "sinonimoak": ["hondamendia", "hondamena", "galmena"] },
  { "id": 204, "hitza": "galdarak", "sinonimoak": ["pertzak", "eltzeak", "maskeluak"] },
  { "id": 205, "hitza": "galdu", "sinonimoak": ["hondatu", "mindu", "alferrik galdu"] },
  { "id": 206, "hitza": "gale", "sinonimoak": ["desira", "nahi", "gogo"] },
  { "id": 207, "hitza": "galgatu", "sinonimoak": ["balaztatu", "geldiarazi", "gelditu"] },
  { "id": 208, "hitza": "gaurko", "sinonimoak": ["oraingo", "egungo", "gaur egungo"] },
  { "id": 209, "hitza": "gazi-geza", "sinonimoak": ["gazi-gozoa", "gezamina"] },
  { "id": 210, "hitza": "gaztigu", "sinonimoak": ["abisu", "mezu", "jakinarazpen"] },
  { "id": 211, "hitza": "gela", "sinonimoak": ["areto", "sala"] },
  { "id": 212, "hitza": "geldiro", "sinonimoak": ["astiro", "poliki", "betaro"] },
  { "id": 213, "hitza": "gertaera", "sinonimoak": ["jazoera", "gertakari"] },
  { "id": 214, "hitza": "gibelaldean", "sinonimoak": ["atzealdean", "bizkarraldean"] },
  { "id": 215, "hitza": "gisako", "sinonimoak": ["moduko", "antzeko", "pareko"] },
  { "id": 216, "hitza": "gizen", "sinonimoak": ["lodi", "potolo", "obeso"] },
  { "id": 217, "hitza": "gogoangarritzat", "sinonimoak": ["oroigarritzat", "gomutagarritzat", "gogoragarritzat"] },
  { "id": 218, "hitza": "gogoeta", "sinonimoak": ["hausnarketa", "pentsaketa", "azterketa"] },
  { "id": 219, "hitza": "gogoko", "sinonimoak": ["gustuko", "atsegin", "laket"] },
  { "id": 220, "hitza": "goibel", "sinonimoak": ["betilun", "triste", "hits"] },
  { "id": 221, "hitza": "goititu", "sinonimoak": ["altxatu", "jaso", "goratu"] },
  { "id": 222, "hitza": "gorabeherak", "sinonimoak": ["ajeak", "gaitzak", "minak"] },
  { "id": 223, "hitza": "gorazarre", "sinonimoak": ["omenaldi", "goraipamen", "gorespen"] },
  { "id": 224, "hitza": "gorputzaren", "sinonimoak": ["soinaren"] },
  { "id": 225, "hitza": "gorrotoa", "sinonimoak": ["herra", "higuina", "hegigoa"] },
  { "id": 226, "hitza": "gotzain", "sinonimoak": ["apezpiku"] },
  { "id": 227, "hitza": "greba", "sinonimoak": ["lanuztea", "huelga"] },
  { "id": 228, "hitza": "gurdi", "sinonimoak": ["orga", "karro"] },
  { "id": 229, "hitza": "guritzen", "sinonimoak": ["beratzen", "biguntzen", "samurtzen"] },
  { "id": 230, "hitza": "gutizia", "sinonimoak": ["apeta", "gurari", "nahiera"] },
  { "id": 231, "hitza": "gutxikoa", "sinonimoak": ["eskasekoa", "urrikoa", "txikikoa"] },
  { "id": 232, "hitza": "haatik", "sinonimoak": ["hala ere", "alabaina", "alta"] },
  { "id": 233, "hitza": "haginik", "sinonimoak": ["hortzik", "hortz-haginik", "hortzeriarik"] },
  { "id": 234, "hitza": "haitzulo", "sinonimoak": ["kobazulo", "leize", "harpe"] },
  { "id": 235, "hitza": "haizatzeko", "sinonimoak": ["aireztatzeko", "egurasteko", "airatzeko"] },
  { "id": 236, "hitza": "hamarkada", "sinonimoak": ["hamarraldi", "hamarte"] },
  { "id": 237, "hitza": "hanpatuta", "sinonimoak": ["puztuta", "handituta", "hantuta"] },
  { "id": 238, "hitza": "hantuste", "sinonimoak": ["harrokeria", "handikeria", "burgoikeria"] },
  { "id": 239, "hitza": "haranik", "sinonimoak": ["bailararik", "ibarrik", "sakanik"] },
  { "id": 240, "hitza": "harraskan", "sinonimoak": ["sukaltarrian", "txurrutarrian", "dalan"] },
  { "id": 241, "hitza": "hautesten", "sinonimoak": ["aukeratzen", "hautatzen", "izendatzen"] },
  { "id": 242, "hitza": "heldutakoan", "sinonimoak": ["umotutakoan", "ondutakoan", "zoritutakoan"] },
  { "id": 243, "hitza": "herbal", "sinonimoak": ["ahul", "makal", "indarge"] },
  { "id": 244, "hitza": "herren", "sinonimoak": ["maingu", "trankin", "hanka-motz"] },
  { "id": 245, "hitza": "herrenbelak", "sinonimoak": ["akastunak", "narriodunak"] },
  { "id": 246, "hitza": "hertsigoa", "sinonimoak": ["itxiagoa", "estuagoa", "meharragoa"] },
  { "id": 247, "hitza": "hezea", "sinonimoak": ["umela", "ezkoa", "bustia"] },
  { "id": 248, "hitza": "higi", "sinonimoak": ["mugi"] },
  { "id": 249, "hitza": "hilbeila", "sinonimoak": ["gaubeila", "beila"] },
  { "id": 250, "hitza": "hilekoa", "sinonimoak": ["soldata", "hilerokoa", "hilabetekoa"] },
  { "id": 251, "hitza": "hiltzear", "sinonimoak": ["hilzorian", "hiletsian", "hiltamuan"] },
  { "id": 252, "hitza": "hirigunean", "sinonimoak": ["erdigunean", "erdialdean"] },
  { "id": 253, "hitza": "hiritarrei", "sinonimoak": ["kaletarrei", "hirikoei", "kalekoei"] },
  { "id": 254, "hitza": "hisitia", "sinonimoak": ["burugogorra", "setatia", "tematsua"] },
  { "id": 255, "hitza": "hits", "sinonimoak": ["triste", "zurbil", "goibel"] },
  { "id": 256, "hitza": "hitz", "sinonimoak": ["berba", "ele", "solas"] },
  { "id": 257, "hitza": "hitzarmen", "sinonimoak": ["itun", "akordio", "tratu"] },
  { "id": 258, "hitza": "hitzaurrea", "sinonimoak": ["aitzinsolasa", "sarrera", "atarikoa"] },
  { "id": 259, "hitza": "hitzontzia", "sinonimoak": ["hiztuna", "berritsua", "eleketaria"] },
  { "id": 260, "hitza": "hizketan", "sinonimoak": ["berriketan", "eleketan", "berbetan"] },
  { "id": 261, "hitza": "hoba ez", "sinonimoak": ["jakina", "bai horixe", "ezin uka"] },
  { "id": 262, "hitza": "hobariekin", "sinonimoak": ["etekinekin", "mozkinekin", "irabaziekin"] },
  { "id": 263, "hitza": "hobenduna", "sinonimoak": ["erruduna", "egilea", "kulpaduna"] },
  { "id": 264, "hitza": "hobira", "sinonimoak": ["lurpera", "ehortz", "hilobira"] },
  { "id": 265, "hitza": "hondakin", "sinonimoak": ["zabor", "zakar", "zarama"] },
  { "id": 266, "hitza": "hondamena", "sinonimoak": ["hondamendia", "ausiabartza", "suntsitzea"] },
  { "id": 267, "hitza": "hots", "sinonimoak": ["dei", "deiadar", "kasu"] },
  { "id": 268, "hitza": "hunkigarria", "sinonimoak": ["zirraragarria"] },
  { "id": 269, "hitza": "hurkoa", "sinonimoak": ["ondokoa", "albokoa", "hurbilekoa"] },
  { "id": 270, "hitza": "huskeria", "sinonimoak": ["txikikeria", "ezerezkeria", "zirtzileria"] },
  { "id": 271, "hitza": "huts", "sinonimoak": ["kale"] },
  { "id": 272, "hitza": "iaioa", "sinonimoak": ["trebea", "abila", "antzetsua"] },
  { "id": 273, "hitza": "ibilgu", "sinonimoak": ["korridore", "pasillo"] },
  { "id": 274, "hitza": "idoro", "sinonimoak": ["aurkitu", "ediren", "topatu"] },
  { "id": 275, "hitza": "idortea", "sinonimoak": ["lehorteea", "sikatea", "agorteea"] },
  { "id": 276, "hitza": "igandean", "sinonimoak": ["domekan"] },
  { "id": 277, "hitza": "igarri", "sinonimoak": ["asmatu", "antzeman", "sumatu"] },
  { "id": 278, "hitza": "igorriko", "sinonimoak": ["bidaliko", "helaraziko"] },
  { "id": 279, "hitza": "ihardesteko", "sinonimoak": ["erantzuteko", "kontra egiteko", "trabak jartzeko"] },
  { "id": 280, "hitza": "ihartu", "sinonimoak": ["zimeldu", "maskaldu", "zapuztu"] },
  { "id": 281, "hitza": "ikerketa", "sinonimoak": ["ikerkuntza", "ikertze", "ikerlan"] },
  { "id": 282, "hitza": "ikuskapen", "sinonimoak": ["ikuskatze", "miaketa", "araketa"] },
  { "id": 283, "hitza": "ikuspegi", "sinonimoak": ["panorama", "ikusmira", "bista"] },
  { "id": 284, "hitza": "ilemotots", "sinonimoak": ["iletxorta", "ile-txirikorda", "txirikorda"] },
  { "id": 285, "hitza": "ilundura", "sinonimoak": ["tristura", "nahigabe", "atsekabe"] },
  { "id": 286, "hitza": "iluntzean", "sinonimoak": ["ilunabarrean", "ilunsentian", "gau aldean"] },
  { "id": 287, "hitza": "imajina", "sinonimoak": ["eman", "jo", "pentsa"] },
  { "id": 288, "hitza": "imintzioka", "sinonimoak": ["keinuka"] },
  { "id": 289, "hitza": "inarrak", "sinonimoak": ["txinpartak", "pindarrak", "txinkak"] },
  { "id": 290, "hitza": "inarrosteko", "sinonimoak": ["hunkitzeko", "astintzeko", "asaldatzeko"] },
  { "id": 291, "hitza": "inauteriak", "sinonimoak": ["aratusteak", "inauteak"] },
  { "id": 292, "hitza": "indabak", "sinonimoak": ["babarrunak", "mailarrak"] },
  { "id": 293, "hitza": "indarkeria", "sinonimoak": ["bortxakeria", "gogorkeria", "biolentzia"] },
  { "id": 294, "hitza": "indartu", "sinonimoak": ["sendotu", "bizkortu", "azkartu"] },
  { "id": 295, "hitza": "indriska", "sinonimoak": ["euri-jasa", "zaparrada", "zaldizkoa"] },
  { "id": 296, "hitza": "induskatzeko", "sinonimoak": ["hondeatzeko", "zulatzeko"] },
  { "id": 297, "hitza": "ingumekin", "sinonimoak": ["iratxoekin"] },
  { "id": 298, "hitza": "injustizia", "sinonimoak": ["bidegabekeria", "zuzengabekeria"] },
  { "id": 299, "hitza": "inkesta", "sinonimoak": ["galdeketa", "itaunketa"] },
  { "id": 300, "hitza": "inoiz", "sinonimoak": ["sekula", "egundo", "nehoiz"] },
  { "id": 301, "hitza": "inozokeria", "sinonimoak": ["lelokeria", "tentelkeria", "ergelkeria"] },
  { "id": 302, "hitza": "instituziotara", "sinonimoak": ["erakundetara"] },
  { "id": 303, "hitza": "intziriak", "sinonimoak": ["aieneak", "auhenak", "erostake"] },
  { "id": 304, "hitza": "inuritu", "sinonimoak": ["lokartu", "sorgortu", "logaletu"] },
  { "id": 305, "hitza": "ipini", "sinonimoak": ["jarri", "paratu"] },
  { "id": 306, "hitza": "ipurdikoa", "sinonimoak": ["ipurkada", "ipurdikada", "mokorkada"] },
  { "id": 307, "hitza": "ipurterrea", "sinonimoak": ["erretxina", "kakapirria", "triperrea"] },
  { "id": 308, "hitza": "irabazkin", "sinonimoak": ["mozkin", "etekin", "hobari"] },
  { "id": 309, "hitza": "iragaitza", "sinonimoak": ["bidea", "etorrera", "iristea"] },
  { "id": 310, "hitza": "iragarri", "sinonimoak": ["jakinarazi", "aditzera eman", "adierazi"] },
  { "id": 311, "hitza": "iraindu", "sinonimoak": ["laidotu", "laidotzatu", "laidetsi"] },
  { "id": 312, "hitza": "iraitz", "sinonimoak": ["bota", "egotz", "bidal"] },
  { "id": 313, "hitza": "iratzarri", "sinonimoak": ["esnatu", "atzarrri", "ernatu"] },
  { "id": 314, "hitza": "iraundor", "sinonimoak": ["etengabe", "jarraitu", "iragangaitz"] },
  { "id": 315, "hitza": "iraungi", "sinonimoak": ["itzali", "amatatu", "hil"] },
  { "id": 316, "hitza": "irekitzeko", "sinonimoak": ["zabaltzeko"] },
  { "id": 317, "hitza": "irigarri", "sinonimoak": ["barregarri", "lotsagarri"] },
  { "id": 318, "hitza": "irion", "sinonimoak": ["gastatu", "xahutu", "zarrasteldu"] },
  { "id": 319, "hitza": "irmotasunaz", "sinonimoak": ["sendotasunaz", "tinkotasunaz", "finkotasunaz"] },
  { "id": 320, "hitza": "isilean", "sinonimoak": ["ezkutuan", "sekretupean", "isilpean"] },
  { "id": 321, "hitza": "iskanbilak", "sinonimoak": ["liskarrak", "kalapitak", "zalapartak"] },
  { "id": 322, "hitza": "istinga", "sinonimoak": ["lupetza", "lokatza", "basatza"] },
  { "id": 323, "hitza": "istorio", "sinonimoak": ["pasadizo", "kontu", "gauza"] },
  { "id": 324, "hitza": "itsu-itsuan", "sinonimoak": ["itsumustuka", "itsutuki", "itsuki"] },
  { "id": 325, "hitza": "itsukeria", "sinonimoak": ["setakeria", "egoskorkeria", "burugogorkeria"] },
  { "id": 326, "hitza": "itzalpea", "sinonimoak": ["gerizpea", "geriza", "itzala"] },
  { "id": 327, "hitza": "itzelezo", "sinonimoak": ["izugarrizko", "ikaragarrrizko", "sekulako"] },
  { "id": 328, "hitza": "izenburua", "sinonimoak": ["idazpurua", "titulua", "goiburukoa"] },
  { "id": 329, "hitza": "izenpetu", "sinonimoak": ["sinatu", "firmatu", "onartu"] },
  { "id": 330, "hitza": "izotzez", "sinonimoak": ["jelaz", "hormaz", "leiaz"] },
  { "id": 331, "hitza": "izutia", "sinonimoak": ["beldurtia", "ikaratia", "koldarra"] },
  { "id": 332, "hitza": "jabaldu", "sinonimoak": ["lasaitu", "baretu", "trankildu"] },
  { "id": 333, "hitza": "jagoten", "sinonimoak": ["zaintzen", "artatzen", "begiratzen"] },
  { "id": 334, "hitza": "jaiak", "sinonimoak": ["festak", "bestak"] },
  { "id": 335, "hitza": "jaikitzen", "sinonimoak": ["altxatzen"] },
  { "id": 336, "hitza": "jaioterria", "sinonimoak": ["sorterria"] },
  { "id": 337, "hitza": "jaitsiera", "sinonimoak": ["beheratze", "beherakada", "jaiste"] },
  { "id": 338, "hitza": "jaki", "sinonimoak": ["elikagai", "janari", "jangai"] },
  { "id": 339, "hitza": "jakin", "sinonimoak": ["zehatz", "berezi", "konkretu"] },
  { "id": 340, "hitza": "jakina", "sinonimoak": ["ezagun", "agerikoa", "nabaria"] },
  { "id": 341, "hitza": "jakina", "sinonimoak": ["horixe", "noski"] },
  { "id": 342, "hitza": "jakitatea", "sinonimoak": ["jakituria", "jakinduria", "jakintasuna"] },
  { "id": 343, "hitza": "jangalea", "sinonimoak": ["jangura", "apetitoa"] },
  { "id": 344, "hitza": "jantzia", "sinonimoak": ["ikasia", "jakituna", "jakintsua"] },
  { "id": 345, "hitza": "jantztegi", "sinonimoak": ["arropategi", "aldagela"] },
  { "id": 346, "hitza": "jaurti", "sinonimoak": ["bota", "egotzi", "esan"] },
  { "id": 347, "hitza": "jausi", "sinonimoak": ["erori"] },
  { "id": 348, "hitza": "jelatuta", "sinonimoak": ["izotzuta", "hormatuta", "leituta"] },
  { "id": 349, "hitza": "jeloskeriagatik", "sinonimoak": ["bekaizkeriagatik", "inbidiagatik", "ondamuagatik"] },
  { "id": 350, "hitza": "jendetasunez", "sinonimoak": ["gizalegez", "adeitasunez", "gizabidez"] },
  { "id": 351, "hitza": "jendetza", "sinonimoak": ["jendeketa", "jendealdia", "jende-pila"] },
  { "id": 352, "hitza": "jesan", "sinonimoak": ["eskatu", "galdatu", "galdegin"] },
  { "id": 353, "hitza": "jesartzen", "sinonimoak": ["esertzen", "ipintzen", "kokatzen"] },
  { "id": 354, "hitza": "jetzi", "sinonimoak": ["eraitsi", "bildu", "batu"] },
  { "id": 355, "hitza": "jeurt", "sinonimoak": ["atzera"] },
  { "id": 356, "hitza": "jipoia", "sinonimoak": ["astindua", "astinaldia", "astinketa"] },
  { "id": 357, "hitza": "jirabira", "sinonimoak": ["itzulinguru", "ingurumaril"] },
  { "id": 358, "hitza": "jiratu", "sinonimoak": ["biratu", "bihurtu", "itzuli"] },
  { "id": 359, "hitza": "jiten", "sinonimoak": ["etortzen", "heltzen", "iristen"] },
  { "id": 360, "hitza": "jitoan", "sinonimoak": ["noraezean", "bertan behera"] },
  { "id": 361, "hitza": "joaldi", "sinonimoak": ["kontzertu", "emanaldi", "saio"] },
  { "id": 362, "hitza": "joera", "sinonimoak": ["jaugina", "grina", "ganua"] },
  { "id": 363, "hitza": "jokabidea", "sinonimoak": ["jokera", "jokamoldea", "portaera"] },
  { "id": 364, "hitza": "jomugara", "sinonimoak": ["helburura", "xedera"] },
  { "id": 365, "hitza": "jorratuko", "sinonimoak": ["landuko", "aztertuko", "ikusiko"] },
  { "id": 366, "hitza": "josia", "sinonimoak": ["betea", "gainezka", "goraino"] },
  { "id": 367, "hitza": "jostetan", "sinonimoak": ["olgetan", "jolasean", "jostaketan"] },
  { "id": 368, "hitza": "jujeen", "sinonimoak": ["epaileen", "jujarien"] },
  { "id": 369, "hitza": "jukutria", "sinonimoak": ["txandrio", "azpijoko", "azpikeria"] },
  { "id": 370, "hitza": "junpatzen", "sinonimoak": ["kulunkatzen", "zabunkatzen", "zarabandatzen"] },
  { "id": 371, "hitza": "juzgu", "sinonimoak": ["iritzi", "uste", "aburu"] },
  { "id": 372, "hitza": "kabartu", "sinonimoak": ["lehortu", "idortu", "sikatu"] },
  { "id": 373, "hitza": "kabugabea", "sinonimoak": ["amaigabea", "azkengabea", "mugagabea"] },
  { "id": 374, "hitza": "kadiratik", "sinonimoak": ["jarlekutik", "aulkitik", "jesarlekutik"] },
  { "id": 375, "hitza": "kaialdeko", "sinonimoak": ["portualdeko"] },
  { "id": 376, "hitza": "kailutsua", "sinonimoak": ["maskurtsua", "gogortua", "mokortua"] },
  { "id": 377, "hitza": "kaioak", "sinonimoak": ["antxetak", "kalatxoriak"] },
  { "id": 378, "hitza": "kakazkeria", "sinonimoak": ["doilorkeria", "zitalkeria", "gizatzarkeria"] },
  { "id": 379, "hitza": "kakaztu", "sinonimoak": ["zaputzu", "hondatu", "alferrik galdu"] },
  { "id": 380, "hitza": "kalte", "sinonimoak": ["gaitz", "min"] },
  { "id": 381, "hitza": "kamutsa", "sinonimoak": ["maketsa", "lanputsa"] },
  { "id": 382, "hitza": "kaskutsik", "sinonimoak": ["buru hutsik"] },
  { "id": 383, "hitza": "katanarrua", "sinonimoak": ["diru-zorroa"] },
  { "id": 384, "hitza": "kebide", "sinonimoak": ["kezulo", "tximinia"] },
  { "id": 385, "hitza": "keinatu", "sinonimoak": ["mehatxatu", "zemaitu", "larderiatu"] },
  { "id": 386, "hitza": "keko-meko", "sinonimoak": ["zalantzan", "dudatsu", "ezbaian"] },
  { "id": 387, "hitza": "kemenez", "sinonimoak": ["gogoz", "adorez", "kalipuz"] },
  { "id": 388, "hitza": "kerratu", "sinonimoak": ["galdu", "mindu", "garraztu"] },
  { "id": 389, "hitza": "kerura", "sinonimoak": ["kiratsera", "sundara", "hatsera"] },
  { "id": 390, "hitza": "kexarik", "sinonimoak": ["kexurik", "arrangurarik", "ahuenik"] },
  { "id": 391, "hitza": "kezkatzeko", "sinonimoak": ["arduratzeko", "larritzeko", "urduritzeko"] },
  { "id": 392, "hitza": "kidekoak", "sinonimoak": ["antzekoak", "berdintsuak", "parekoak"] },
  { "id": 393, "hitza": "kikirrioa", "sinonimoak": ["zakila", "buztana", "armagia"] },
  { "id": 394, "hitza": "kilimon", "sinonimoak": ["porrot", "molokot", "kiebra"] },
  { "id": 395, "hitza": "kimatzeaz", "sinonimoak": ["inausteaz", "adaontzeaz", "mozteaz"] },
  { "id": 396, "hitza": "kimu", "sinonimoak": ["puja", "aldaxka", "muskil"] },
  { "id": 397, "hitza": "kirian", "sinonimoak": ["segidan", "ordenan", "hurrenkeran"] },
  { "id": 398, "hitza": "kirtenetatik", "sinonimoak": ["giderretatik", "heldulekuetatik", "eskulekuetatik"] },
  { "id": 399, "hitza": "kisikilkeria", "sinonimoak": ["bilaukeria", "zitalkeria", "dongekeria"] },
  { "id": 400, "hitza": "kitzikatu", "sinonimoak": ["berotu"] },
  { "id": 401, "hitza": "koadro", "sinonimoak": ["margolan", "pintura", "artelan"] },
  { "id": 402, "hitza": "koipetsu", "sinonimoak": ["koipeztu", "ugerdo", "krakatsu"] },
  { "id": 403, "hitza": "kokorroa", "sinonimoak": ["zakarra", "oiesa", "kaskarroa"] },
  { "id": 404, "hitza": "kokospe", "sinonimoak": ["girgilo"] },
  { "id": 405, "hitza": "komuna", "sinonimoak": ["ohikoa", "arrunta", "agizkoa"] },
  { "id": 406, "hitza": "koskortzen", "sinonimoak": ["hazten", "handitzen", "tarrotzen"] },
  { "id": 407, "hitza": "kraskaturik", "sinonimoak": ["pitzaturik", "arrakalaturik", "arraildurik"] },
  { "id": 408, "hitza": "kukutzea", "sinonimoak": ["estaltzea", "ezkutatzea", "ostentzea"] },
  { "id": 409, "hitza": "kukuxean", "sinonimoak": ["zokomiran", "ikusmiran", "usainka"] },
  { "id": 410, "hitza": "kutsadura", "sinonimoak": ["poluzioa"] },
  { "id": 411, "hitza": "kutsua", "sinonimoak": ["ukitua", "eragina", "azentua"] },
  { "id": 412, "hitza": "labainkorra", "sinonimoak": ["irristakorra", "lerrakorra", "limurkorra"] },
  { "id": 413, "hitza": "laborariak", "sinonimoak": ["nekazariak", "baserritarrak"] },
  { "id": 414, "hitza": "laborria", "sinonimoak": ["ikara", "izua", "beldurra"] },
  { "id": 415, "hitza": "laga", "sinonimoak": ["utzi", "mailegatu"] },
  { "id": 416, "hitza": "lagungarri", "sinonimoak": ["onuragarri", "mesedegarri", "probetxugarri"] },
  { "id": 417, "hitza": "laguntzaileek", "sinonimoak": ["azafatek", "harreragileek"] },
  { "id": 418, "hitza": "lainotu", "sinonimoak": ["hodeitu", "goibeldu", "ilundu"] },
  { "id": 419, "hitza": "laket", "sinonimoak": ["atsegin", "gogoko", "gustuko"] },
  { "id": 420, "hitza": "lanabes", "sinonimoak": ["tresna", "erreminta", "langai"] },
  { "id": 421, "hitza": "lanaldi", "sinonimoak": ["lansaio", "lanegun", "jardunaldi"] },
  { "id": 422, "hitza": "landerra", "sinonimoak": ["txiroa", "behartsua", "erromesa"] },
  { "id": 423, "hitza": "landua", "sinonimoak": ["jasoa", "zaindua", "laboratua"] },
  { "id": 424, "hitza": "lanpasean", "sinonimoak": ["zerrian"] },
  { "id": 425, "hitza": "latza", "sinonimoak": ["gogorra", "bortitza", "zaila"] },
  { "id": 426, "hitza": "laudorioa", "sinonimoak": ["goraipamena", "gorespena", "handiespena"] },
  { "id": 427, "hitza": "lausenguak", "sinonimoak": ["losintxak", "koipekeriak", "balakuak"] },
  { "id": 428, "hitza": "laztanak", "sinonimoak": ["ferekak", "txerak"] },
  { "id": 429, "hitza": "legetxe", "sinonimoak": ["legez", "bezala", "adina"] },
  { "id": 430, "hitza": "lehenengoa", "sinonimoak": ["lehenbizikoa", "aurrenekoa", "estreinakoa"] },
  { "id": 431, "hitza": "lehengo", "sinonimoak": ["aurreko", "behin"] },
  { "id": 432, "hitza": "lehia", "sinonimoak": ["borroka", "norgehiagoka", "konkurrentzia"] },
  { "id": 433, "hitza": "leize", "sinonimoak": ["alde", "desberdintasun", "amildegi"] },
  { "id": 434, "hitza": "lekukotuz", "sinonimoak": ["bertakotuz", "tokikotuz", "sustraituz"] },
  { "id": 435, "hitza": "leporaino", "sinonimoak": ["goraino", "beterik", "gainezka"] },
  { "id": 436, "hitza": "lerdea", "sinonimoak": ["adurra"] },
  { "id": 437, "hitza": "lerdendu", "sinonimoak": ["liraindu", "zardaitu", "edertu"] },
  { "id": 438, "hitza": "leundu", "sinonimoak": ["bigundu", "baretu", "eztitu"] },
  { "id": 439, "hitza": "libro", "sinonimoak": ["aske", "libre", "nahierara"] },
  { "id": 440, "hitza": "ligain", "sinonimoak": ["gartxu", "jangartxu", "urri-jale"] },
  { "id": 441, "hitza": "likitsa", "sinonimoak": ["zikina", "lizuna", "lohia"] },
  { "id": 442, "hitza": "lili", "sinonimoak": ["lore"] },
  { "id": 443, "hitza": "liluragarria", "sinonimoak": ["xarmagarria", "zoragarria", "itsugarria"] },
  { "id": 444, "hitza": "lipartxo", "sinonimoak": ["unetxo", "istant", "aldiune"] },
  { "id": 445, "hitza": "liskarrean", "sinonimoak": ["iskanbilan", "haserrean", "ika-mika"] },
  { "id": 446, "hitza": "lixiba", "sinonimoak": ["bokata", "gobada"] },
  { "id": 447, "hitza": "lodrota", "sinonimoak": ["lodia", "gizena", "potoloa"] },
  { "id": 448, "hitza": "lokarriak", "sinonimoak": ["axubetak", "estekailuak"] },
  { "id": 449, "hitza": "loriagarri", "sinonimoak": ["zoragarri", "liluragarria", "txundigarria"] },
  { "id": 450, "hitza": "lorratzek", "sinonimoak": ["aztarnek", "oinatzek", "herexek"] },
  { "id": 451, "hitza": "lumatu", "sinonimoak": ["bipildu", "ziplatu"] },
  { "id": 452, "hitza": "luzetsi", "sinonimoak": ["berantetsi", "kezkatu", "larritu"] },
  { "id": 453, "hitza": "magalean", "sinonimoak": ["altzoan", "galtzarrean", "kolkoan"] },
  { "id": 454, "hitza": "mahaikide", "sinonimoak": ["bazkaltiar", "bazkalkide", "jankide"] },
  { "id": 455, "hitza": "mainontzia", "sinonimoak": ["mainatia", "negartia", "negarrotza"] },
  { "id": 456, "hitza": "maisutasun", "sinonimoak": ["trebetasun", "abilezia", "maina"] },
  { "id": 457, "hitza": "maitagarria", "sinonimoak": ["zoragarria", "liluragarria", "xarmagarria"] },
  { "id": 458, "hitza": "maitale", "sinonimoak": ["amorante", "ohaide", "ohelagun"] },
  { "id": 459, "hitza": "maiztasun", "sinonimoak": ["sarritasun", "ohikotasun", "jarraitutasun"] },
  { "id": 460, "hitza": "maizterrarekin", "sinonimoak": ["errentariarekin", "akuradunarekin", "etxetiarrarekin"] },
  { "id": 461, "hitza": "makurra", "sinonimoak": ["dongea", "zitala", "gaiztoa"] },
  { "id": 462, "hitza": "marmarka", "sinonimoak": ["xuxurlaka", "murrmurioka", "txutxu-mutxuka"] },
  { "id": 463, "hitza": "maskal", "sinonimoak": ["makal", "ahul", "pattal"] },
  { "id": 464, "hitza": "meatsa", "sinonimoak": ["argala", "mehea", "makarra"] },
  { "id": 465, "hitza": "meharretan", "sinonimoak": ["estuetan", "hertsietan", "itxietan"] },
  { "id": 466, "hitza": "mehatxua", "sinonimoak": ["zemaia", "dixidua"] },
  { "id": 467, "hitza": "melatuta", "sinonimoak": ["bustita", "blaituta"] },
  { "id": 468, "hitza": "mendratu", "sinonimoak": ["gutxitu", "urritu", "eskastu"] },
  { "id": 469, "hitza": "mesedegarri", "sinonimoak": ["lagungarri", "onuragarri", "probetxugarri"] },
  { "id": 470, "hitza": "mihietan", "sinonimoak": ["ahotan", "aho-mihitan", "mingainetan"] },
  { "id": 471, "hitza": "mihiseak", "sinonimoak": ["izarak", "maindireak"] },
  { "id": 472, "hitza": "mikatza", "sinonimoak": ["mingotsa", "mingarra", "karmina"] },
  { "id": 473, "hitza": "milika", "sinonimoak": ["mizkin", "milinga"] },
  { "id": 474, "hitza": "mintzagai", "sinonimoak": ["hizpide", "berbabide", "elepide"] },
  { "id": 475, "hitza": "mirabe", "sinonimoak": ["morroi", "otsein", "sehi"] },
  { "id": 476, "hitza": "mirailean", "sinonimoak": ["ispiluan"] },
  { "id": 477, "hitza": "moduzkotasunez", "sinonimoak": ["apaintasunez", "garbitasunez", "txukuntasunez"] },
  { "id": 478, "hitza": "moja", "sinonimoak": ["lekaime", "serora"] },
  { "id": 479, "hitza": "mokoka", "sinonimoak": ["errietan", "ika-mika", "sesioan"] },
  { "id": 480, "hitza": "mokordoa", "sinonimoak": ["lotsagabea", "petrala", "ozarra"] },
  { "id": 481, "hitza": "moldatzen", "sinonimoak": ["konpontzen"] },
  { "id": 482, "hitza": "mordotu", "sinonimoak": ["pilatu", "metatu", "bildu"] },
  { "id": 483, "hitza": "motroiloa", "sinonimoak": ["potxoloa", "piporra", "zaparrotea"] },
  { "id": 484, "hitza": "mozkindu", "sinonimoak": ["sardakatu", "inausi", "kimatu"] },
  { "id": 485, "hitza": "mudakortasuna", "sinonimoak": ["ezegonkortasuna", "aldakortasuna", "aldaberatasuna"] },
  { "id": 486, "hitza": "mugarriak", "sinonimoak": ["zedarriak", "mugaldeak", "muturrak"] },
  { "id": 487, "hitza": "mukizu", "sinonimoak": ["umemoko", "umegorri", "umekondo"] },
  { "id": 488, "hitza": "mukuru", "sinonimoak": ["beteta", "gainezka", "lepo"] },
  { "id": 489, "hitza": "murriztu", "sinonimoak": ["beheratu", "merkatu", "jaitsi"] },
  { "id": 490, "hitza": "musu-truk", "sinonimoak": ["doan", "debalde", "urririk"] },
  { "id": 491, "hitza": "mutiltzen", "sinonimoak": ["lumatzen", "bipiltzen"] },
  { "id": 492, "hitza": "muturreko", "sinonimoak": ["ukabilko", "zartako", "ukabilkada"] },
  { "id": 493, "hitza": "nabaritzen", "sinonimoak": ["nabarmetzen", "igartzen", "antzematen"] },
  { "id": 494, "hitza": "nabarriak", "sinonimoak": ["arreak", "arreskak", "jaspeztatuak"] },
  { "id": 495, "hitza": "nagikeria", "sinonimoak": ["alferkeria", "zabarkeria", "utzikeria"] },
  { "id": 496, "hitza": "nagusitu", "sinonimoak": ["gailendu", "garaitu", "nabarmendu"] },
  { "id": 497, "hitza": "nahasgarria", "sinonimoak": ["nahasian", "nahaspilatsuan", "ilunean"] },
  { "id": 498, "hitza": "nahikari", "sinonimoak": ["desira", "irrika", "lera"] },
  { "id": 499, "hitza": "nahita", "sinonimoak": ["gurata", "berariaz", "propio"] },
  { "id": 500, "hitza": "nakan", "sinonimoak": ["orezta", "orin", "natu"] },
  { "id": 501, "hitza": "nakez", "sinonimoak": ["gaitz", "zailki", "kostata"] },
  { "id": 502, "hitza": "narrio", "sinonimoak": ["akats", "oker", "hutsegite"] },
  { "id": 503, "hitza": "nasaia", "sinonimoak": ["zabala", "lasaia", "arina"] },
  { "id": 504, "hitza": "naturan", "sinonimoak": ["izadian"] },
  { "id": 505, "hitza": "nazkagarria", "sinonimoak": ["higuingarria", "nardagarria"] },
  { "id": 506, "hitza": "negargarria", "sinonimoak": ["zoritzar", "ezbehar", "malur"] },
  { "id": 507, "hitza": "nerabetasuna", "sinonimoak": ["nerabezaroa", "adoleszentzia"] },
  { "id": 508, "hitza": "neroni", "sinonimoak": ["neuri", "niri"] },
  { "id": 509, "hitza": "neurdin", "sinonimoak": ["dena dela", "nolanahi ere", "edonola ere"] },
  { "id": 510, "hitza": "neurriko", "sinonimoak": ["tamainako", "moduko", "dimentsioko"] },
  { "id": 511, "hitza": "neurtezina", "sinonimoak": ["neurgaitza", "neurgea"] },
  { "id": 512, "hitza": "nihaur", "sinonimoak": ["ni", "neu", "nerau"] },
  { "id": 513, "hitza": "niketz", "sinonimoak": ["nire partez", "nire aldetik", "nire izenean"] },
  { "id": 514, "hitza": "ninikatzen", "sinonimoak": ["kimatzen", "muskiltzen", "ernamutntzen"] },
  { "id": 515, "hitza": "ninikierarik", "sinonimoak": ["umekeriarik", "haurkeriarik", "seinkeriarik"] },
  { "id": 516, "hitza": "nobedaderen", "sinonimoak": ["berriren", "albisteren"] },
  { "id": 517, "hitza": "nobela", "sinonimoak": ["eleberri"] },
  { "id": 518, "hitza": "noharroinari", "sinonimoak": ["behartsuari", "txiroari", "pobreri"] },
  { "id": 519, "hitza": "noiznahi", "sinonimoak": ["edonoiz", "noiznahi den", "noizgura"] },
  { "id": 520, "hitza": "noiztik", "sinonimoak": ["noizdanik"] },
  { "id": 521, "hitza": "nokuak", "sinonimoak": ["akatsak", "hutsuneak", "gabeziak"] },
  { "id": 522, "hitza": "nolakatu", "sinonimoak": ["bihurtu", "bilakatu"] },
  { "id": 523, "hitza": "nolakotasuna", "sinonimoak": ["ezaugarria", "tasuna", "dohaina"] },
  { "id": 524, "hitza": "nolanahiko", "sinonimoak": ["edonolako", "edozein", "halako"] },
  { "id": 525, "hitza": "nongotasuna", "sinonimoak": ["jatorria", "sorlekua", "sorterria"] },
  { "id": 526, "hitza": "nonzeberri", "sinonimoak": ["kontaktilu", "autubatzaile", "eleberriti"] },
  { "id": 527, "hitza": "norabide", "sinonimoak": ["noranzko", "norako"] },
  { "id": 528, "hitza": "norgehiagoka", "sinonimoak": ["partida", "norlehenka", "lehia"] },
  { "id": 529, "hitza": "normalean", "sinonimoak": ["oro har", "eskuarki", "orokorrean"] },
  { "id": 530, "hitza": "nortasunaz", "sinonimoak": ["izaeraz", "jiteaz", "aiurriaz"] },
  { "id": 531, "hitza": "noski", "sinonimoak": ["jakina", "noskiro", "ez horixe"] },
  { "id": 532, "hitza": "nozitu", "sinonimoak": ["pairatu", "jasan", "izan"] },
  { "id": 533, "hitza": "ñabardura", "sinonimoak": ["xehetasun", "zehaztasun", "zehazkizun"] },
  { "id": 534, "hitza": "ñaka", "sinonimoak": ["txandrio", "engainu", "iruzur"] },
  { "id": 535, "hitza": "ñauka", "sinonimoak": ["miauka", "marrakaka", "mauka"] },
  { "id": 536, "hitza": "ñiki-ñaka", "sinonimoak": ["txortan", "larrutan", "txikili-txakala"] },
  { "id": 537, "hitza": "ñimiñoaren", "sinonimoak": ["ñarroaren", "txikiaren", "ttipiaren"] },
  { "id": 538, "hitza": "ñir-ñir", "sinonimoak": ["dir-dir", "diz-diz"] },
  { "id": 539, "hitza": "objektoreek", "sinonimoak": ["eragozleek"] },
  { "id": 540, "hitza": "obratzen", "sinonimoak": ["libratzen", "sabelusten", "kaka egiten"] },
  { "id": 541, "hitza": "odolatuz", "sinonimoak": ["ubelduz", "ubelduraz", "beltzunez"] },
  { "id": 542, "hitza": "odolberoarekin", "sinonimoak": ["haserrekorrarekin", "suminkorrarekin", "suharrarekin"] },
  { "id": 543, "hitza": "odolkiak", "sinonimoak": ["odolosteak", "tripotak", "tripotxak"] },
  { "id": 544, "hitza": "ofizioz", "sinonimoak": ["lanbidez", "ogibidez", "bizibidez"] },
  { "id": 545, "hitza": "ogasundun", "sinonimoak": ["aberats", "ondasundun", "ukandun"] },
  { "id": 546, "hitza": "ohaide", "sinonimoak": ["ohelagun", "amorante", "maitale"] },
  { "id": 547, "hitza": "ohargarri", "sinonimoak": ["nabarmenki", "nabariki", "argiro"] },
  { "id": 548, "hitza": "oharkabekeria", "sinonimoak": ["axolagabekeria", "arduragabekeria", "zabarkeria"] },
  { "id": 549, "hitza": "oharpenei", "sinonimoak": ["oharrei", "gaztiguei", "oharkizunei"] },
  { "id": 550, "hitza": "ohilduta", "sinonimoak": ["uxatuta", "aienatuta", "izututa"] },
  { "id": 551, "hitza": "ohinak", "sinonimoak": ["lapurrak", "ebasleak"] },
  { "id": 552, "hitza": "ohitura", "sinonimoak": ["usadio", "aztura", "ekandu"] },
  { "id": 553, "hitza": "oiesa", "sinonimoak": ["baldarra", "trauskila", "zakarra"] },
  { "id": 554, "hitza": "oiherrra", "sinonimoak": ["bihurria", "okerra", "makurra"] },
  { "id": 555, "hitza": "oihuka", "sinonimoak": ["garrasika", "deiadarka", "txilioka"] },
  { "id": 556, "hitza": "oilotu", "sinonimoak": ["koldartu", "kikildu", "uzkurtu"] },
  { "id": 557, "hitza": "oinarria", "sinonimoak": ["funttsa", "harroina", "abiaburua"] },
  { "id": 558, "hitza": "oinatz", "sinonimoak": ["aztarna", "zantzu", "arrasto"] },
  { "id": 559, "hitza": "oinatzargi", "sinonimoak": ["tximistargi", "tximista", "oinatzarri"] },
  { "id": 560, "hitza": "oinazegarria", "sinonimoak": ["mingarria", "samingarria", "atsekabegarria"] },
  { "id": 561, "hitza": "oinordekoa", "sinonimoak": ["jabegaia", "jaraunslea"] },
  { "id": 562, "hitza": "oinutsik", "sinonimoak": ["ortozik", "hanka hutsik", "zankuts"] },
  { "id": 563, "hitza": "okaztagarria", "sinonimoak": ["kirasduna", "nazkagarria", "higuingarria"] },
  { "id": 564, "hitza": "okela", "sinonimoak": ["haragi", "haragiki", "txitxi"] },
  { "id": 565, "hitza": "oker", "sinonimoak": ["erratuta", "tronpatuta", "alferrik"] },
  { "id": 566, "hitza": "okerragotu", "sinonimoak": ["areagotu", "larriagotu", "gaizkiagotu"] },
  { "id": 567, "hitza": "olagarroa", "sinonimoak": ["eskuluzea"] },
  { "id": 568, "hitza": "oldarkorra", "sinonimoak": ["grinatsua", "gartsua", "suharra"] },
  { "id": 569, "hitza": "oldozketa", "sinonimoak": ["gogoeta", "hausnarketa", "pentsaketa"] },
  { "id": 570, "hitza": "olerkintzarekin", "sinonimoak": ["poemagintzarekin", "poesiagintzarekin"] },
  { "id": 571, "hitza": "omenaldia", "sinonimoak": ["gorazarrea"] },
  { "id": 572, "hitza": "onartu", "sinonimoak": ["onetsi", "aitortu", "baietsi"] },
  { "id": 573, "hitza": "onbeharrak", "sinonimoak": ["pobreziak", "miseriak", "txirotasunak"] },
  { "id": 574, "hitza": "onbera", "sinonimoak": ["onegia", "on hutsa", "bihotzbera"] },
  { "id": 575, "hitza": "ondarea", "sinonimoak": ["oinordea", "ondoregoa", "jaraunspena"] },
  { "id": 576, "hitza": "ondikoz", "sinonimoak": ["tamalez", "zoritxarrez", "maluruski"] },
  { "id": 577, "hitza": "ondoko", "sinonimoak": ["alboko", "aldameneko", "pareko"] },
  { "id": 578, "hitza": "ondu", "sinonimoak": ["hobetu", "hobekitu", "oneratu"] },
  { "id": 579, "hitza": "oniritzia", "sinonimoak": ["onespena", "onarpena", "baimena"] },
  { "id": 580, "hitza": "ontsa", "sinonimoak": ["ido", "ongi", "ederki"] },
  { "id": 581, "hitza": "onturre", "sinonimoak": ["onura", "probetxu", "etekin"] },
  { "id": 582, "hitza": "oparotasun", "sinonimoak": ["ugaritasun", "joritasun", "narotasun"] },
  { "id": 583, "hitza": "oratu", "sinonimoak": ["ekin", "lotu", "eman"] },
  { "id": 584, "hitza": "ordaindu", "sinonimoak": ["jasan", "pairatu", "sufritu"] },
  { "id": 585, "hitza": "ordea", "sinonimoak": ["ostera", "aldiz", "berriz"] },
  { "id": 586, "hitza": "orobat", "sinonimoak": ["halaber", "era berean"] },
  { "id": 587, "hitza": "oroiren", "sinonimoak": ["oroitzapen", "gogorapen", "gomuta"] },
  { "id": 588, "hitza": "orraztua", "sinonimoak": ["orrazketa", "berrikustea", "gainbegiratua"] },
  { "id": 589, "hitza": "osoro", "sinonimoak": ["osorik", "guztiz", "goraino"] },
  { "id": 590, "hitza": "ospetsua", "sinonimoak": ["entzutetsua", "sonatua", "aipatua"] },
  { "id": 591, "hitza": "ospitale", "sinonimoak": ["erietxe", "eritegi"] },
  { "id": 592, "hitza": "ostiralean", "sinonimoak": ["barikuan", "ortziralean"] },
  { "id": 593, "hitza": "otoi", "sinonimoak": ["mesedez", "arren", "faborez"] },
  { "id": 594, "hitza": "otu", "sinonimoak": ["bururatu", "gogoratu"] },
  { "id": 595, "hitza": "otzantzen", "sinonimoak": ["mantsozten", "hezten", "menderatzen"] },
  { "id": 596, "hitza": "otzara", "sinonimoak": ["saski", "otarre", "zare"] },
  { "id": 597, "hitza": "oztopo", "sinonimoak": ["eragozpen", "traba", "zoztor"] },
  { "id": 598, "hitza": "pagotxa", "sinonimoak": ["mauka", "mantxunga", "txoko"] },
  { "id": 599, "hitza": "pairagarri", "sinonimoak": ["jasangarri", "onargarri", "eramangarri"] },
  { "id": 600, "hitza": "pairu", "sinonimoak": ["egonarri", "eroapen", "pairamen"] },
  { "id": 601, "hitza": "paku", "sinonimoak": ["paga", "soldata", "ordainsari"] },
  { "id": 602, "hitza": "panpinaren", "sinonimoak": ["andrakilaren"] },
  { "id": 603, "hitza": "panpox", "sinonimoak": ["polit", "eder", "pinpirin"] },
  { "id": 604, "hitza": "papaitak", "sinonimoak": ["asmakizunak", "igarkizunak"] },
  { "id": 605, "hitza": "paraje", "sinonimoak": ["inguru", "leku", "txoko"] },
  { "id": 606, "hitza": "paratu", "sinonimoak": ["jarri", "ipini"] },
  { "id": 607, "hitza": "parekatu", "sinonimoak": ["erkatu", "alderatu", "konparatu"] },
  { "id": 608, "hitza": "pario", "sinonimoak": ["apustu", "postura", "dema"] },
  { "id": 609, "hitza": "pariztak", "sinonimoak": ["keinuak", "imintzioak", "inki-minkiak"] },
  { "id": 610, "hitza": "pasadizoak", "sinonimoak": ["istorioak", "bitxikeriak", "gertakariak"] },
  { "id": 611, "hitza": "pauso", "sinonimoak": ["urrats", "oinkada"] },
  { "id": 612, "hitza": "pegar", "sinonimoak": ["tupina", "txantxil", "suil"] },
  { "id": 613, "hitza": "pellokeria", "sinonimoak": ["ergelkeria", "kaikukeria", "kirtenkeria"] },
  { "id": 614, "hitza": "pentsakor", "sinonimoak": ["gogoetatsu", "hausnartzaile", "pentsatzailea"] },
  { "id": 615, "hitza": "pentzutan", "sinonimoak": ["ardurapean", "kontu", "pentzudan"] },
  { "id": 616, "hitza": "perkatxa", "sinonimoak": ["arretatsua", "maratza", "arduratsua"] },
  { "id": 617, "hitza": "perpausaren", "sinonimoak": ["esaldiaren", "esakuntzaren", "esakunearen"] },
  { "id": 618, "hitza": "peskizan", "sinonimoak": ["itxaropenean", "zain", "esperoan"] },
  { "id": 619, "hitza": "petraldu", "sinonimoak": ["txartu", "usteldu", "zaputzu"] },
  { "id": 620, "hitza": "pilpilka", "sinonimoak": ["pilpiraka", "taupaka", "taupadaka"] },
  { "id": 621, "hitza": "piltzar", "sinonimoak": ["zarpail", "pilda", "zarpa"] },
  { "id": 622, "hitza": "pinpirintzen", "sinonimoak": ["apaintzen", "dotoretzen", "panpinatzen"] },
  { "id": 623, "hitza": "pinportak", "sinonimoak": ["pikorrak", "garauak", "pikortak"] },
  { "id": 624, "hitza": "piper", "sinonimoak": ["sasieskola", "txikarra"] },
  { "id": 625, "hitza": "pisutsuak", "sinonimoak": ["astunak", "pisudunak"] },
  { "id": 626, "hitza": "pitinkeria", "sinonimoak": ["huskeria", "txikikeria", "zirtzileria"] },
  { "id": 627, "hitza": "pitzadurak", "sinonimoak": ["arrakalak", "arrailak", "artesiak"] },
  { "id": 628, "hitza": "piura", "sinonimoak": ["itxura", "eitea", "taxua"] },
  { "id": 629, "hitza": "pizgarri", "sinonimoak": ["eragingarri", "bizigarri", "akuilu"] },
  { "id": 630, "hitza": "piztia", "sinonimoak": ["basapiztia", "patari", "ihizi"] },
  { "id": 631, "hitza": "piztu", "sinonimoak": ["isiotu", "irazeki", "izeki"] },
  { "id": 632, "hitza": "ponitu", "sinonimoak": ["ordaindu", "pagatu", "konpondu"] },
  { "id": 633, "hitza": "pozgabetu", "sinonimoak": ["nahigabetu", "atsekabetu", "goibeldu"] },
  { "id": 634, "hitza": "prezioan", "sinonimoak": ["salneurrian"] },
  { "id": 635, "hitza": "programak", "sinonimoak": ["egitarauak"] },
  { "id": 636, "hitza": "proguzko", "sinonimoak": ["doluzko", "lutozko"] },
  { "id": 637, "hitza": "prometatu", "sinonimoak": ["agindu", "hitzeman", "prometsu"] },
  { "id": 638, "hitza": "pulunpatua", "sinonimoak": ["murgildua", "sartua", "harrapatua"] },
  { "id": 639, "hitza": "purrustaka", "sinonimoak": ["marmarka", "marmarioka", "sarramuskaka"] },
  { "id": 640, "hitza": "pusketarik", "sinonimoak": ["zatirik", "puskarik", "tatorik"] },
  { "id": 641, "hitza": "putzu", "sinonimoak": ["osin", "zulo", "istil"] },
  { "id": 642, "hitza": "puztu", "sinonimoak": ["harropuztu", "hanpatu", "harrotu"] },
  { "id": 643, "hitza": "sabaian", "sinonimoak": ["mandioan", "lastategian", "belartegian"] },
  { "id": 644, "hitza": "sabelandi", "sinonimoak": ["tripontzi", "jatun", "sabelkoi"] },
  { "id": 645, "hitza": "sabelgorriak", "sinonimoak": ["basatiak", "ankerrak", "bihotzgabeak"] },
  { "id": 646, "hitza": "sagarno", "sinonimoak": ["sagardo"] },
  { "id": 647, "hitza": "sagarroia", "sinonimoak": ["trikua", "kirikinoa"] },
  { "id": 648, "hitza": "saihesbide", "sinonimoak": ["desbideratze"] },
  { "id": 649, "hitza": "saihests", "sinonimoak": ["alderdi", "alde", "puntu"] },
  { "id": 650, "hitza": "sailkatu", "sinonimoak": ["ordenatu", "antolatu", "apailatu"] },
  { "id": 651, "hitza": "saiokoak", "sinonimoak": ["ahaleginak", "ekinaldiak", "saialdiak"] },
  { "id": 652, "hitza": "sakela", "sinonimoak": ["patrika", "poltsiko"] },
  { "id": 653, "hitza": "salgai", "sinonimoak": ["salkizun", "salmentan", "saltzen"] },
  { "id": 654, "hitza": "saltsa", "sinonimoak": ["nahaspila", "zalaparta", "katramila"] },
  { "id": 655, "hitza": "samalda", "sinonimoak": ["mordoa", "andana", "piloa"] },
  { "id": 656, "hitza": "samurtzeko", "sinonimoak": ["biguntzeko", "hunkitzeko", "leuntzeko"] },
  { "id": 657, "hitza": "santutu", "sinonimoak": ["bedeinkatu", "donesti", "sagaratu"] },
  { "id": 658, "hitza": "sarbidea", "sinonimoak": ["sarrera", "sartzea", "atea"] },
  { "id": 659, "hitza": "sarealdian", "sinonimoak": ["sarekadan"] },
  { "id": 660, "hitza": "saria", "sinonimoak": ["ordainsaria", "donaria", "golardoa"] },
  { "id": 661, "hitza": "sarraskirik", "sinonimoak": ["triskantzarik", "txikiziorik", "sakailarik"] },
  { "id": 662, "hitza": "sarritan", "sinonimoak": ["askotan", "maiz", "usu"] },
  { "id": 663, "hitza": "sasien", "sinonimoak": ["sastraken", "sasitzen", "sastrakadien"] },
  { "id": 664, "hitza": "sastakoetako", "sinonimoak": ["labankadetako", "aiztokadetako", "sastadetako"] },
  { "id": 665, "hitza": "sastarrez", "sinonimoak": ["zaborrez", "zakarrez", "zaramaz"] },
  { "id": 666, "hitza": "segizio", "sinonimoak": ["jarraipen", "segida", "ondorio"] },
  { "id": 667, "hitza": "segur aski", "sinonimoak": ["ziur asko", "ziurrenik", "segurutik"] },
  { "id": 668, "hitza": "seinale", "sinonimoak": ["adierazgarri", "froga", "erakusgarri"] },
  { "id": 669, "hitza": "semebitxia", "sinonimoak": ["seme pontekoa", "seme besoetakoa"] },
  { "id": 670, "hitza": "sendagaitzak", "sinonimoak": ["osagaitzak"] },
  { "id": 671, "hitza": "sendoro", "sinonimoak": ["tinko", "irmoki", "sendo(ki)"] },
  { "id": 672, "hitza": "senekoa", "sinonimoak": ["izaerakoa", "aiurrikoa", "setakoa"] },
  { "id": 673, "hitza": "senitartekorik", "sinonimoak": ["seniderik", "familiarrik", "ahaiderik"] },
  { "id": 674, "hitza": "senperrenak", "sinonimoak": ["gorriak", "senperrak", "beltzak"] },
  { "id": 675, "hitza": "senteriaren", "sinonimoak": ["ongizatearen"] },
  { "id": 676, "hitza": "sentiberatasun", "sinonimoak": ["sentikortasun", "minberatasun", "gaitzikortasun"] },
  { "id": 677, "hitza": "serioski", "sinonimoak": ["benetan", "egitan", "zinez"] },
  { "id": 678, "hitza": "setaturik", "sinonimoak": ["tematurik", "hisiaturik", "gogorturik"] },
  { "id": 679, "hitza": "sigi-sagan", "sinonimoak": ["esemeseka", "harat-honatean"] },
  { "id": 680, "hitza": "siku", "sinonimoak": ["ziplo", "zerraldo"] },
  { "id": 681, "hitza": "simaurra", "sinonimoak": ["ongarri", "gorotza", "satsa"] },
  { "id": 682, "hitza": "sineste", "sinonimoak": ["sinesmen", "sineskera", "ideia"] },
  { "id": 683, "hitza": "sinkusa", "sinonimoak": ["aitzakia", "estakuru", "desenkusa"] },
  { "id": 684, "hitza": "sirats", "sinonimoak": ["atsegin", "plazer", "gustu"] },
  { "id": 685, "hitza": "soberako", "sinonimoak": ["gehiegizko", "neurriz gaineko", "demaseko"] },
  { "id": 686, "hitza": "soilketa", "sinonimoak": ["mozketa", "ebaketa", "botatzea"] },
  { "id": 687, "hitza": "soingainean", "sinonimoak": ["bizkarrean", "lepoan", "sorbaldan"] },
  { "id": 688, "hitza": "solastatzen", "sinonimoak": ["mintzatzen", "elekatzen", "mintzo"] },
  { "id": 689, "hitza": "soluzioren", "sinonimoak": ["konponbideren", "irtenbideren", "aterabideren"] },
  { "id": 690, "hitza": "sorrera", "sinonimoak": ["hastapena", "jatorria", "iturburua"] },
  { "id": 691, "hitza": "suertatu", "sinonimoak": ["egokitu", "egon", "izan"] },
  { "id": 692, "hitza": "sumatzen", "sinonimoak": ["igartzen", "nabaritzen", "antzematen"] },
  { "id": 693, "hitza": "tairik", "sinonimoak": ["etenik", "geldialdirik", "etenaldirik"] },
  { "id": 694, "hitza": "taka-taka", "sinonimoak": ["tipi-tapa", "pitinka-pitinka", "gutxika-gutxika"] },
  { "id": 695, "hitza": "talapastatu", "sinonimoak": ["nahasi", "nahastatu", "irauli"] },
  { "id": 696, "hitza": "taldekatuko", "sinonimoak": ["multzokatuko", "elkartuko", "batuko"] },
  { "id": 697, "hitza": "talkaren", "sinonimoak": ["kolpearen", "danbatekoaren", "kroskaren"] },
  { "id": 698, "hitza": "tamainan", "sinonimoak": ["primeran", "ederto", "bikain"] },
  { "id": 699, "hitza": "tamalgarria", "sinonimoak": ["penagarria", "deitoragarria", "damugarria"] },
  { "id": 700, "hitza": "tanatu", "sinonimoak": ["jausi", "erori", "galdu"] },
  { "id": 701, "hitza": "tankera", "sinonimoak": ["itxura", "eite", "irudi"] },
  { "id": 702, "hitza": "tapaki", "sinonimoak": ["burusi", "manta"] },
  { "id": 703, "hitza": "tarrapatan", "sinonimoak": ["arrapaladan", "zistuan", "itsumustuan"] },
  { "id": 704, "hitza": "taxurik", "sinonimoak": ["mainarik", "trebeziarik", "arterik"] },
  { "id": 705, "hitza": "taxutu", "sinonimoak": ["prestatu", "antolatu", "eratu"] },
  { "id": 706, "hitza": "teiuak", "sinonimoak": ["lizunak", "likitsak", "lohiak"] },
  { "id": 707, "hitza": "tekua", "sinonimoak": ["kiratsa", "kerua", "sunda"] },
  { "id": 708, "hitza": "temakeria", "sinonimoak": ["setakeria", "burugogorkeria", "egoskorkeria"] },
  { "id": 709, "hitza": "tenorez", "sinonimoak": ["garaiz", "sasoiz", "astiz"] },
  { "id": 710, "hitza": "tenperaturan", "sinonimoak": ["hobeberoan"] },
  { "id": 711, "hitza": "tentagarria", "sinonimoak": ["erakargarria", "zirikagarria", "desiragarria"] },
  { "id": 712, "hitza": "tenteldu", "sinonimoak": ["txepeldu", "tontotu", "ergeldu"] },
  { "id": 713, "hitza": "tentetzen", "sinonimoak": ["zutitzen", "zutuntzen"] },
  { "id": 714, "hitza": "tentutik", "sinonimoak": ["senetik", "onetik"] },
  { "id": 715, "hitza": "terrenta", "sinonimoak": ["ohikeria", "errutina", "ohitura"] },
  { "id": 716, "hitza": "testiguak", "sinonimoak": ["lekukoak"] },
  { "id": 717, "hitza": "testuinguruan", "sinonimoak": ["ingurubarrean", "ingurunean", "egoeran"] },
  { "id": 718, "hitza": "tetele-metele", "sinonimoak": ["tontoki", "axolagabeki", "funtsgabeki"] },
  { "id": 719, "hitza": "tinkoagoak", "sinonimoak": ["sendoagoak", "irmoagoak", "finkoagoak"] },
  { "id": 720, "hitza": "tipilgorriak", "sinonimoak": ["biluziak", "biluzgorriak", "larrugorriak"] },
  { "id": 721, "hitza": "tirabira", "sinonimoak": ["liskarra", "eztabaida", "kalapita"] },
  { "id": 722, "hitza": "tiragaleak", "sinonimoak": ["nagiak", "sagaiak"] },
  { "id": 723, "hitza": "tirriagarria", "sinonimoak": ["desiragarria", "tentagarria", "erakargarria"] },
  { "id": 724, "hitza": "tirtirina", "sinonimoak": ["poxpolina", "pertxenta", "mari-apaina"] },
  { "id": 725, "hitza": "toildu", "sinonimoak": ["nagitu", "alfertu", "zabartu"] },
  { "id": 726, "hitza": "tokoloa", "sinonimoak": ["potoloa", "lodikotea", "papalotea"] },
  { "id": 727, "hitza": "tontorrera", "sinonimoak": ["gailurrera", "erpinera", "gora"] },
  { "id": 728, "hitza": "tortilla", "sinonimoak": ["arrautzopila"] },
  { "id": 729, "hitza": "traba", "sinonimoak": ["oztopo", "enbarazu", "eragozpen"] },
  { "id": 730, "hitza": "trankildu", "sinonimoak": ["naretu", "lasaitu", "ibitu"] },
  { "id": 731, "hitza": "tranpati", "sinonimoak": ["iruzurti", "amarrutsu", "azpijale"] },
  { "id": 732, "hitza": "trapadu", "sinonimoak": ["mozkote", "potolo", "zaparrote"] },
  { "id": 733, "hitza": "traturik", "sinonimoak": ["harremanik", "tratabiderik", "erlaziorik"] },
  { "id": 734, "hitza": "trebatzeko", "sinonimoak": ["gaitzeko", "hornitzeko", "ikasteko"] },
  { "id": 735, "hitza": "trenkatuz", "sinonimoak": ["moztuz", "eragotziz", "oztopatuz"] },
  { "id": 736, "hitza": "trimindu", "sinonimoak": ["txikitu", "suntsitu", "birrindu"] },
  { "id": 737, "hitza": "triskilatu", "sinonimoak": ["suntsitu", "hondatu", "birrindu"] },
  { "id": 738, "hitza": "tronpatu", "sinonimoak": ["erratu", "okertu", "nahastu"] },
  { "id": 739, "hitza": "trufaka", "sinonimoak": ["isekaka", "burlaka", "txantxaka"] },
  { "id": 740, "hitza": "trukatzen", "sinonimoak": ["ematen", "egiten", "aldatzen"] },
  { "id": 741, "hitza": "trumilka", "sinonimoak": ["tropelka", "saldoka", "samaldaka"] },
  { "id": 742, "hitza": "tunka", "sinonimoak": ["umore", "aldarte", "gogo"] },
  { "id": 743, "hitza": "txainku", "sinonimoak": ["herren", "maingu", "trankin"] },
  { "id": 744, "hitza": "txaldantzen", "sinonimoak": ["txepeltzen", "ergeltzen", "lelotzen"] },
  { "id": 745, "hitza": "txalogarria", "sinonimoak": ["laudagarria", "goresgarria", "goragarria"] },
  { "id": 746, "hitza": "txanbila", "sinonimoak": ["pegarra", "suila", "txantxila"] },
  { "id": 747, "hitza": "txarkeria", "sinonimoak": ["gaiztakeria", "bihurrikeria", "deabrukeria"] },
  { "id": 748, "hitza": "txarretsi", "sinonimoak": ["gaitzetsi", "ezetsi", "hastandu"] },
  { "id": 749, "hitza": "txatxu", "sinonimoak": ["txotxolo", "txepel", "ganorabako"] },
  { "id": 750, "hitza": "txepeldu", "sinonimoak": ["kikildu", "beldurtu", "koldartu"] },
  { "id": 751, "hitza": "txerrikeria", "sinonimoak": ["zikinkeria", "lohi", "zabor"] },
  { "id": 752, "hitza": "txertatu", "sinonimoak": ["eman", "tartekatu", "egokitu"] },
  { "id": 753, "hitza": "txikertu", "sinonimoak": ["txiki(ago)tu", "murriztu", "gutxitu"] },
  { "id": 754, "hitza": "txikietsi", "sinonimoak": ["mespretxatu", "erdeinatu", "gutxietsi"] },
  { "id": 755, "hitza": "tximarro", "sinonimoak": ["txima", "zarpa", "ilaje"] },
  { "id": 756, "hitza": "tximista", "sinonimoak": ["oinaztura", "oinaztarri", "oinazkar"] },
  { "id": 757, "hitza": "txintxoa", "sinonimoak": ["formala", "ona", "zentzuzkoa"] },
  { "id": 758, "hitza": "txiripa", "sinonimoak": ["zorte", "zori", "asturru"] },
  { "id": 759, "hitza": "txiroen", "sinonimoak": ["pobreen", "behartsuen", "landerren"] },
  { "id": 760, "hitza": "txirriporro", "sinonimoak": ["zalaparta", "harrabots", "zarata"] },
  { "id": 761, "hitza": "txirrist", "sinonimoak": ["laprast", "labain", "irrist"] },
  { "id": 762, "hitza": "txit", "sinonimoak": ["guztiz", "zeharo", "biziki"] },
  { "id": 763, "hitza": "txitean-pitean", "sinonimoak": ["maiz", "sarri", "usu"] },
  { "id": 764, "hitza": "txo", "sinonimoak": ["to", "txotxo", "motel"] },
  { "id": 765, "hitza": "txoil", "sinonimoak": ["guztiz", "erabat", "arras"] },
  { "id": 766, "hitza": "txoratuta", "sinonimoak": ["txora-txora eginda", "liluratuta", "xarmatuta"] },
  { "id": 767, "hitza": "txorrotxoak", "sinonimoak": ["txioak", "txinttak", "txiruliruak"] },
  { "id": 768, "hitza": "txortan", "sinonimoak": ["larrutan", "ñaka", "txikili-txakala"] },
  { "id": 769, "hitza": "txotxina", "sinonimoak": ["kaskarina", "txolina", "txoriburua"] },
  { "id": 770, "hitza": "txukuntzea", "sinonimoak": ["egokitzea", "prestatzea", "atontzea"] },
  { "id": 771, "hitza": "txundigarriak", "sinonimoak": ["harrigarriak", "espantagarriak", "bitxiak"] },
  { "id": 772, "hitza": "txunxturreraino", "sinonimoak": ["tontorreraino", "gailurreraino", "goraino"] },
  { "id": 773, "hitza": "ubeldu", "sinonimoak": ["ilundu", "beltztu", "goibeldu"] },
  { "id": 774, "hitza": "ubidea", "sinonimoak": ["ibilgua", "ibilbidea", "erretena"] },
  { "id": 775, "hitza": "udagoieneko", "sinonimoak": ["udazkeneko"] },
  { "id": 776, "hitza": "udaletxea", "sinonimoak": ["herriko etxea", "herri-etxea"] },
  { "id": 777, "hitza": "udare", "sinonimoak": ["madari"] },
  { "id": 778, "hitza": "ugaldu", "sinonimoak": ["ugaritu", "gehigotu", "areagotu"] },
  { "id": 779, "hitza": "ugazaba", "sinonimoak": ["nagusi", "ostalari", "ostaler"] },
  { "id": 780, "hitza": "ugerrak", "sinonimoak": ["herdoilak", "oxidoak"] },
  { "id": 781, "hitza": "uhanditzen", "sinonimoak": ["harroputzen", "hanpatzen", "harrotzen"] },
  { "id": 782, "hitza": "uharak", "sinonimoak": ["uberak", "lorratzak", "arrastoak"] },
  { "id": 783, "hitza": "ukazio", "sinonimoak": ["ukapen", "ezezko", "ukamen"] },
  { "id": 784, "hitza": "ukuilua", "sinonimoak": ["korta", "abeltegia"] },
  { "id": 785, "hitza": "ulerkorragoa", "sinonimoak": ["adikorragoa", "adeitsuagoa", "harkorragoa"] },
  { "id": 786, "hitza": "ulituko", "sinonimoak": ["koldartuko", "kikilduko", "uzkurtuko"] },
  { "id": 787, "hitza": "uluka", "sinonimoak": ["uhurika", "ainurika"] },
  { "id": 788, "hitza": "umeldu", "sinonimoak": ["hezetu", "ezkotu", "busti"] },
  { "id": 789, "hitza": "umeteria", "sinonimoak": ["haurreria", "haur-taldea", "haur-jendea"] },
  { "id": 790, "hitza": "umilak", "sinonimoak": ["apalak", "xumeak", "xeheak"] },
  { "id": 791, "hitza": "umoretsu", "sinonimoak": ["pozik", "alai", "alegera"] },
  { "id": 792, "hitza": "umotu", "sinonimoak": ["heldu", "nagusitu", "haginak berdindu"] },
  { "id": 793, "hitza": "unagarria", "sinonimoak": ["nekagarria", "aspergarria", "gogaikarria"] },
  { "id": 794, "hitza": "upategia", "sinonimoak": ["arandegia", "ardangela", "upeletegia"] },
  { "id": 795, "hitza": "uraldiak", "sinonimoak": ["uholdeak", "urpetzeak"] },
  { "id": 796, "hitza": "urardotu", "sinonimoak": ["hutsaldu", "desitxuratu", "desnaturalizatu"] },
  { "id": 797, "hitza": "urburu", "sinonimoak": ["iturburu", "iturbegi", "iturri"] },
  { "id": 798, "hitza": "urdailean", "sinonimoak": ["sabelean"] },
  { "id": 799, "hitza": "urdekeriarik", "sinonimoak": ["txerrikeriarik", "zikinkeriarik", "zerrikeriarik"] },
  { "id": 800, "hitza": "urdindu", "sinonimoak": ["zuritu"] },
  { "id": 801, "hitza": "urduritasuna", "sinonimoak": ["artegatasuna", "larritasuna", "egonezina"] },
  { "id": 802, "hitza": "uretaratuko", "sinonimoak": ["pulunpatuko", "urperatuko", "murgilduko"] },
  { "id": 803, "hitza": "urgazle", "sinonimoak": ["laguntzaile", "kolaboratzaile"] },
  { "id": 804, "hitza": "urgoia", "sinonimoak": ["lotsatia", "herabetia", "uzkurra"] },
  { "id": 805, "hitza": "urkultzen", "sinonimoak": ["aletzen", "bihitzen", "garautzen"] },
  { "id": 806, "hitza": "urmaelean", "sinonimoak": ["urloan", "putzuan", "istilean"] },
  { "id": 807, "hitza": "urpera", "sinonimoak": ["hondora", "honda", "murgilaraz"] },
  { "id": 808, "hitza": "urradura", "sinonimoak": ["ebakia", "zauria", "arrakala"] },
  { "id": 809, "hitza": "urratzen", "sinonimoak": ["hausten", "puskatzen"] },
  { "id": 810, "hitza": "urregorririk", "sinonimoak": ["urreirik", "dirurik", "aberastasunik"] },
  { "id": 811, "hitza": "urrendu", "sinonimoak": ["amaitu", "bukatu", "burutu"] },
  { "id": 812, "hitza": "urrikalduz", "sinonimoak": ["gupidatuz", "errukituz", "kupituz"] },
  { "id": 813, "hitza": "urrikoa", "sinonimoak": ["gutxikoa", "eskasekoa", "murritzekoa"] },
  { "id": 814, "hitza": "urripena", "sinonimoak": ["murrizketa", "lerma", "jaitsiera"] },
  { "id": 815, "hitza": "urrundu", "sinonimoak": ["aldendu", "urrutiratu", "lekutu"] },
  { "id": 816, "hitza": "urtabe", "sinonimoak": ["uztaldi", "uztaro", "urtebete"] },
  { "id": 817, "hitza": "urtatu", "sinonimoak": ["urtetsu", "zahar", "aspaldiko"] },
  { "id": 818, "hitza": "urtebetetzea", "sinonimoak": ["urtemuga", "eguna", "urteurrena"] },
  { "id": 819, "hitza": "urtxintxa", "sinonimoak": ["katagorri"] },
  { "id": 820, "hitza": "urtze-garaia", "sinonimoak": ["urtzaldia", "urtzaroa"] },
  { "id": 821, "hitza": "usadio", "sinonimoak": ["ohitura", "ekandu", "aztura"] },
  { "id": 822, "hitza": "usin", "sinonimoak": ["doministiku"] },
  { "id": 823, "hitza": "usnatu", "sinonimoak": ["sumatu", "aditu", "usaindu"] },
  { "id": 824, "hitza": "uspelduraz", "sinonimoak": ["beltzunez", "ubelduraz", "odolbatuaz"] },
  { "id": 825, "hitza": "uspelgune", "sinonimoak": ["laioz", "ospel"] },
  { "id": 826, "hitza": "ustekabean", "sinonimoak": ["ezustean", "itsumustuan", "tupustean"] },
  { "id": 827, "hitza": "usteltzen", "sinonimoak": ["galtzen", "hondatzen", "zapuzten"] },
  { "id": 828, "hitza": "ustez", "sinonimoak": ["aburuz", "iritzi", "irudiko"] },
  { "id": 829, "hitza": "ustiagarria", "sinonimoak": ["erabilgarria", "baliagarria", "aprobetxagarria"] },
  { "id": 830, "hitza": "ustiaketa", "sinonimoak": ["ustiapena", "esplotazioa", "ustiatzea"] },
  { "id": 831, "hitza": "usu", "sinonimoak": ["maiz", "askotan", "sarri"] },
  { "id": 832, "hitza": "utikan", "sinonimoak": ["alde", "ospa", "hanka"] },
  { "id": 833, "hitza": "uxalduko", "sinonimoak": ["zimelduko", "ihartuko", "faunduko"] },
  { "id": 834, "hitza": "uxatzen", "sinonimoak": ["izutzen", "ikaratzen", "beldurtzen"] },
  { "id": 835, "hitza": "uxterra", "sinonimoak": ["samurra", "biguna", "guria"] },
  { "id": 836, "hitza": "uxuka-muxuka", "sinonimoak": ["txuxtu-muxtuka", "xuxurlaka", "murmurioka"] },
  { "id": 837, "hitza": "uzkaili", "sinonimoak": ["irauli"] },
  { "id": 838, "hitza": "uzkaldurik", "sinonimoak": ["loturik", "estekaturik", "josirik"] },
  { "id": 839, "hitza": "uzkurtuta", "sinonimoak": ["koldartuta", "ulituta", "kikilduta"] },
  { "id": 840, "hitza": "uztai", "sinonimoak": ["zirrindola", "zirgilo", "obo"] },
  { "id": 841, "hitza": "uztardura", "sinonimoak": ["lotura", "esteka", "lokarri"] },
  { "id": 842, "hitza": "uztarturik", "sinonimoak": ["antxumaturik", "gurutzaturik"] },
  { "id": 843, "hitza": "xafarratu", "sinonimoak": ["irakuzui", "garbitu", "ikuzi"] },
  { "id": 844, "hitza": "xafla", "sinonimoak": ["xerra(da)", "zati", "puska"] },
  { "id": 845, "hitza": "xahu", "sinonimoak": ["aratz", "garbi", "lasai"] },
  { "id": 846, "hitza": "xahutzaileari", "sinonimoak": ["zarrastelari", "irioleari", "gastatzaileari"] },
  { "id": 847, "hitza": "xai", "sinonimoak": ["soto", "upategi", "biltegi"] },
  { "id": 848, "hitza": "xaki", "sinonimoak": ["marka", "seinale", "ezaugarri"] },
  { "id": 849, "hitza": "xaloa", "sinonimoak": ["atsegina", "xehea", "apala"] },
  { "id": 850, "hitza": "xanfarin", "sinonimoak": ["txoriburu", "nahaba", "kaskarin"] },
  { "id": 851, "hitza": "xantxa", "sinonimoak": ["kaikua", "ontzia", "pertza"] },
  { "id": 852, "hitza": "xapoka", "sinonimoak": ["pixkanaka", "apurka", "pitinka"] },
  { "id": 853, "hitza": "xaribaria", "sinonimoak": ["zalaparta", "azantza", "zarata"] },
  { "id": 854, "hitza": "xarma", "sinonimoak": ["lilura", "erakapen", "xarmadura"] },
  { "id": 855, "hitza": "xatarrak", "sinonimoak": ["pixoihalak", "troxak", "haur-oihalak"] },
  { "id": 856, "hitza": "xauxun", "sinonimoak": ["muturluze", "sarkin", "endreda-makila"] },
  { "id": 857, "hitza": "xaxatuz", "sinonimoak": ["aizkatuz", "zirikatuz", "kinatuz"] },
  { "id": 858, "hitza": "xedatu", "sinonimoak": ["zehaztu", "adierazi", "finkatu"] },
  { "id": 859, "hitza": "xede", "sinonimoak": ["helburu", "asmo", "jomuga"] },
  { "id": 660, "hitza": "xehatu", "sinonimoak": ["txikitu", "birrindu", "zatitu"] },
  { "id": 861, "hitza": "xehetasunen", "sinonimoak": ["zehaztasunen", "argibideren", "azalpenen"] },
  { "id": 862, "hitza": "xelebreak", "sinonimoak": ["gatzdunak", "barregarriak", "txistagarriak"] },
  { "id": 863, "hitza": "xendra", "sinonimoak": ["bidezidor", "bidexka", "basabide"] },
  { "id": 864, "hitza": "xerka", "sinonimoak": ["bila", "arakatzean", "miatzean"] },
  { "id": 865, "hitza": "xerlotsua", "sinonimoak": ["iletsua", "ileduna", "bilotsua"] },
  { "id": 866, "hitza": "xextran", "sinonimoak": ["sesioan", "errietan", "kalapitan"] },
  { "id": 867, "hitza": "xifrialdia", "sinonimoak": ["estualdia", "larrialdia", "itolaldia"] },
  { "id": 868, "hitza": "xikotu", "sinonimoak": ["larrua jo", "txortan egin", "larrutan egin"] },
  { "id": 869, "hitza": "xildre", "sinonimoak": ["korapilo", "begizta", "begite"] },
  { "id": 870, "hitza": "xilintxak", "sinonimoak": ["zintzarriak", "joareak", "arranak"] },
  { "id": 871, "hitza": "ximena", "sinonimoak": ["apaina", "garbia", "txukuna"] },
  { "id": 872, "hitza": "xingilka", "sinonimoak": ["txingoka", "txingoan"] },
  { "id": 873, "hitza": "xingola-mingola", "sinonimoak": ["sigi-sagan", "esemeseka", "alderik alde"] },
  { "id": 874, "hitza": "xiringatu", "sinonimoak": ["injektatu", "txertatu", "jarri"] },
  { "id": 875, "hitza": "xirrika-xarraka", "sinonimoak": ["tipi-tapa", "tirriki-tarraka", "astiro-astiro"] },
  { "id": 876, "hitza": "xitxerra", "sinonimoak": ["txingorra", "kazkabarra", "babazuzua"] },
  { "id": 877, "hitza": "xixkatzea", "sinonimoak": ["iruzur egitea", "ziria sartzea", "irusako egitea"] },
  { "id": 878, "hitza": "xuhur", "sinonimoak": ["zeken", "eskulabur", "zikoitz"] },
  { "id": 879, "hitza": "xukatu", "sinonimoak": ["lehortu", "sikatu", "kendu"] },
  { "id": 880, "hitza": "xumea", "sinonimoak": ["xehea", "apala", "laua"] },
  { "id": 881, "hitza": "xuraila", "sinonimoak": ["hitsa", "zurbila", "beluria"] },
  { "id": 882, "hitza": "xurgatzetik", "sinonimoak": ["zurrupatzetik", "irenstetik", "hurrupatzetik"] },
  { "id": 883, "hitza": "xuxurla", "sinonimoak": ["marmarra", "murmurioa", "zurrumurrua"] },
  { "id": 884, "hitza": "zabaldiek", "sinonimoak": ["ordokiek", "lautadek", "zelaidiek"] },
  { "id": 885, "hitza": "zabaldu", "sinonimoak": ["hedatu", "barreiatu", "iritsi"] },
  { "id": 886, "hitza": "zabalera", "sinonimoak": ["hedadura", "eremua", "esparrua"] },
  { "id": 887, "hitza": "zabalik", "sinonimoak": ["irekirik"] },
  { "id": 888, "hitza": "zabaltza", "sinonimoak": ["terraza", "gaindegia", "gainaaldea"] },
  { "id": 889, "hitza": "zabarkeriaz", "sinonimoak": ["arduragabekeriaz", "utzikeriaz", "axolagabekeriaz"] },
  { "id": 890, "hitza": "zabartu", "sinonimoak": ["axolagabetu", "alfertu", "arduragabetu"] },
  { "id": 891, "hitza": "zabo", "sinonimoak": ["hantura", "handitu", "handitsu"] },
  { "id": 892, "hitza": "zaboilak", "sinonimoak": ["prakak", "galtzak"] },
  { "id": 893, "hitza": "zabor", "sinonimoak": ["zakar(eria)", "zarama", "hondakin"] },
  { "id": 894, "hitza": "zabu", "sinonimoak": ["leria", "kulunka"] },
  { "id": 895, "hitza": "zadora", "sinonimoak": ["kuxidadea", "nahaspila", "anabasa"] },
  { "id": 896, "hitza": "zaflada", "sinonimoak": ["zaplastako", "masailako", "belarrondoko"] },
  { "id": 897, "hitza": "zailaren", "sinonimoak": ["kikirrioaren", "armegainaren", "buztanaren"] },
  { "id": 898, "hitza": "zailduta", "sinonimoak": ["gogortuta", "laztuta", "zakartuta"] },
  { "id": 899, "hitza": "zalapartaka", "sinonimoak": ["arrapaladan", "presaka", "lasterka"] },
  { "id": 900, "hitza": "zaldakatu", "sinonimoak": ["lokaztu", "lohitztatu", "idoiztatu"] },
  { "id": 901, "hitza": "zaletu", "sinonimoak": ["grinatu", "guratu", "nahitu"] },
  { "id": 902, "hitza": "zalukeria", "sinonimoak": ["maltzurkeria", "azerikeria", "faltsukeria"] },
  { "id": 903, "hitza": "zamatu", "sinonimoak": ["sortatu", "kargatu", "bizkarreratuz"] },
  { "id": 904, "hitza": "zanbrotuta", "sinonimoak": ["zimelduta", "ihartuta", "lehortuta"] },
  { "id": 905, "hitza": "zango", "sinonimoak": ["hanka", "berna"] },
  { "id": 906, "hitza": "zankuts", "sinonimoak": ["oinutsik", "ortozik", "hanka hutsik"] },
  { "id": 907, "hitza": "zanpaketa", "sinonimoak": ["zapalkuntza", "errepresioa", "zapalketa"] },
  { "id": 908, "hitza": "zaparrada", "sinonimoak": ["indriska", "euri-jasa", "zaldizko"] },
  { "id": 909, "hitza": "zaputza", "sinonimoak": ["muzina", "mukerra", "betizua"] },
  { "id": 910, "hitza": "zapzipia", "sinonimoak": ["txaplata", "petrala", "pairugabea"] },
  { "id": 911, "hitza": "zaramarra", "sinonimoak": ["azantza", "zalaparta", "iskanbila"] },
  { "id": 912, "hitza": "zarbaildu", "sinonimoak": ["narriatu", "izorratu", "hondatu"] },
  { "id": 913, "hitza": "zarrastelkeria", "sinonimoak": ["xahubidea", "eralketa", "xahutzea"] },
  { "id": 914, "hitza": "zatarreria", "sinonimoak": ["zakarreria", "zaborreria", "satarra"] },
  { "id": 915, "hitza": "zedarrituak", "sinonimoak": ["finkatuak", "xedatuak", "mugatuak"] },
  { "id": 916, "hitza": "zegan", "sinonimoak": ["zenbatean"] },
  { "id": 917, "hitza": "zeharka-meharka", "sinonimoak": ["sigi-sagan", "itzulinguruka", "zeharbidez"] },
  { "id": 918, "hitza": "zeharretara", "sinonimoak": ["saiheska", "soslaiz", "alboz"] },
  { "id": 919, "hitza": "zehatu", "sinonimoak": ["zigortu", "punitu", "gaztigatu"] },
  { "id": 920, "hitza": "zekentzea", "sinonimoak": ["zikoiztea", "diruzaletzea", "xuhurztea"] },
  { "id": 921, "hitza": "zelaia", "sinonimoak": ["landa", "larre", "belardi"] },
  { "id": 922, "hitza": "zelanbait", "sinonimoak": ["nolabait", "nola edo hala", "nolerebait"] },
  { "id": 923, "hitza": "zemaitu", "sinonimoak": ["mehatxatu", "larderiatu", "estutu"] },
  { "id": 924, "hitza": "zenduaren", "sinonimoak": ["hildakoaren", "hilaren", "defuntuaren"] },
  { "id": 925, "hitza": "zentsurarik", "sinonimoak": ["trabarik", "oztoporik", "eragozpenik"] },
  { "id": 926, "hitza": "zentzubekeria", "sinonimoak": ["burugabekeria", "erokeria", "burtzrokeria"] },
  { "id": 927, "hitza": "zeregin", "sinonimoak": ["eginkizun", "funtzio", "eginbehar"] },
  { "id": 928, "hitza": "zergati", "sinonimoak": ["arrazoi", "kari", "zio"] },
  { "id": 929, "hitza": "zerikusia", "sinonimoak": ["harremana", "lotura", "erlazioa"] },
  { "id": 930, "hitza": "zerraldo", "sinonimoak": ["siku", "ziplo", "blaus"] },
  { "id": 931, "hitza": "zerrepeldu", "sinonimoak": ["hotzildu", "epeldu", "hoztu"] },
  { "id": 932, "hitza": "zertzeladei", "sinonimoak": ["zehaztasunei", "xehetasunei", "xehadurei"] },
  { "id": 933, "hitza": "zeruertzean", "sinonimoak": ["zerumugan", "ostertzean", "hodeiertzean"] },
  { "id": 934, "hitza": "zibilizatu", "sinonimoak": ["hezi", "jendetu"] },
  { "id": 935, "hitza": "zihoa", "sinonimoak": ["gantza", "urina", "bilgorra"] },
  { "id": 936, "hitza": "zikiratu", "sinonimoak": ["irendu", "irantzi"] },
  { "id": 937, "hitza": "zildaia", "sinonimoak": ["muturrekoa", "mozala"] },
  { "id": 938, "hitza": "zilegitzeko", "sinonimoak": ["baimentzeko", "onartzeko", "onesteko"] },
  { "id": 939, "hitza": "zimarkua", "sinonimoak": ["iruzurra", "amarrua", "jukutria"] },
  { "id": 940, "hitza": "zimiko", "sinonimoak": ["imurtxi", "atximur(ka)", "txatxamur(ka)"] },
  { "id": 941, "hitza": "zimurkera", "sinonimoak": ["diruzalekeria", "zekenkera", "zuhurrkeria"] },
  { "id": 942, "hitza": "zin-zinez", "sinonimoak": ["bene-benetan", "zinez eta minez", "egia-egitan"] },
  { "id": 943, "hitza": "zindoa", "sinonimoak": ["langilea", "fina", "ondradua"] },
  { "id": 944, "hitza": "zinemaratu", "sinonimoak": ["pantailaratu", "proiektatu", "filmarazi"] },
  { "id": 945, "hitza": "zintzotasunez", "sinonimoak": ["onestasunez", "prestutasunez", "ondradutasunez"] },
  { "id": 946, "hitza": "zintzurkoia", "sinonimoak": ["jatuna", "tripontzia", "salobrea"] },
  { "id": 947, "hitza": "zintzurluenak", "sinonimoak": ["ahozuriak", "mokofinak"] },
  { "id": 948, "hitza": "zira", "sinonimoak": ["kapusaia", "anoraka"] },
  { "id": 949, "hitza": "zirikatzen", "sinonimoak": ["xaxatzen", "ahakatzen", "probokatzen"] },
  { "id": 950, "hitza": "zirko", "sinonimoak": ["extarte", "kalezulo", "sohorna"] },
  { "id": 951, "hitza": "zirpildua", "sinonimoak": ["listua", "altsitua", "pirukatua"] },
  { "id": 952, "hitza": "zirrara", "sinonimoak": ["hunkipen", "sentsazio", "zarrasta"] },
  { "id": 953, "hitza": "zirtzileriak", "sinonimoak": ["purtzilkeriak", "zizki-mizkiak", "huskeriak"] },
  { "id": 954, "hitza": "ziurrenik", "sinonimoak": ["ziur aski", "asko", "segurutik", "segur aski"] },
  { "id": 955, "hitza": "zizini", "sinonimoak": ["asmo", "xede", "uste"] },
  { "id": 956, "hitza": "ziztrin", "sinonimoak": ["txatxar", "hutsal", "purtzil"] },
  { "id": 957, "hitza": "zokoratzen", "sinonimoak": ["bazterreratzen", "alboratzen", "baztertzen"] },
  { "id": 958, "hitza": "zoli", "sinonimoak": ["adi", "erne", "arretatsu"] },
  { "id": 959, "hitza": "zoratzeko", "sinonimoak": ["erotzeko", "txoratzeko", "burutik egiteko"] },
  { "id": 960, "hitza": "zoritzarrekoa", "sinonimoak": ["zorigabekoa", "zorigaiztokoa", "zorigaiztekoa"] },
  { "id": 961, "hitza": "zorritsoz", "sinonimoak": ["zorritsuz", "zikinez", "koipeztoz"] },
  { "id": 962, "hitza": "zorrotzazun", "sinonimoak": ["gogortasun", "zurruntasun", "irmotasun"] },
  { "id": 963, "hitza": "zozotu", "sinonimoak": ["txepeldu", "totolotu", "memelotu"] },
  { "id": 964, "hitza": "zubiototik", "sinonimoak": ["zaldainetik", "pasagunetik", "pasabidetik"] },
  { "id": 665, "hitza": "zuhaitzi", "sinonimoak": ["arboladi", "baso", "oihan"] },
  { "id": 966, "hitza": "zulatzeak", "sinonimoak": ["indusketak", "hondaketak", "prospekzioak"] },
  { "id": 967, "hitza": "zurikeriaka", "sinonimoak": ["losintxaka", "lausenguka", "balakuka"] },
  { "id": 968, "hitza": "zurmindu", "sinonimoak": ["sorgortu", "hozmindu", "gogortu"] },
  { "id": 969, "hitza": "zurturik", "sinonimoak": ["harriturik", "txunditurik", "espantaturik"] },
  { "id": 970, "hitza": "zutundu", "sinonimoak": ["zutitu", "altxatu", "jaiki"] },
  { "id": 971, "hitza": "zutzarturik", "sinonimoak": ["sustraiturik", "erroturik", "bertakoturik"] },
  { "id": 972, "hitza": "zuzeneko", "sinonimoak": ["artez"] }
]
